{"MaxTotalHashRate":2606.1850,"CurrentTotalHashRate":2598.390,"LastUpdateDate":"Apr 22 2018  7:34PM","RIGs":7,"GPUs":85,"Miners":[{ "miner":"Miner01", "MinerID":1024, "cards":13,"IPAddress":"10.0.1.137", "maxhash":391.1960, "hash":373.172,"Min30":0,"Hr2":0,"Hr6":1,"D1":1,"D2":1, "gpus":[{"hash":30.096, "temp":"55", "fan":100},{"hash":14.301, "temp":"83", "fan":100},{"hash":29.637, "temp":"56", "fan":100},{"hash":30.078, "temp":"72", "fan":100},{"hash":30.084, "temp":"60", "fan":100},{"hash":30.090, "temp":"61", "fan":100},{"hash":29.824, "temp":"68", "fan":100},{"hash":30.061, "temp":"69", "fan":100},{"hash":30.096, "temp":"57", "fan":100},{"hash":29.726, "temp":"56", "fan":100},{"hash":29.718, "temp":"59", "fan":100},{"hash":29.719, "temp":"55", "fan":100},{"hash":29.737, "temp":"69", "fan":100}]},{ "miner":"Miner02", "MinerID":1025, "cards":12,"IPAddress":"10.0.1.138", "maxhash":361.0200, "hash":351.713,"Min30":0,"Hr2":0,"Hr6":0,"D1":0,"D2":0, "gpus":[{"hash":30.021, "temp":"58", "fan":83},{"hash":25.625, "temp":"55", "fan":83},{"hash":30.092, "temp":"61", "fan":83},{"hash":30.092, "temp":"59", "fan":83},{"hash":28.979, "temp":"59", "fan":83},{"hash":30.080, "temp":"52", "fan":83},{"hash":29.980, "temp":"42", "fan":83},{"hash":29.104, "temp":"40", "fan":83},{"hash":29.253, "temp":"52", "fan":83},{"hash":29.996, "temp":"43", "fan":83},{"hash":29.231, "temp":"52", "fan":83},{"hash":29.254, "temp":"44", "fan":83}]},{ "miner":"Miner03", "MinerID":1026, "cards":13,"IPAddress":"10.0.1.76", "maxhash":404.9500, "hash":404.667,"Min30":0,"Hr2":0,"Hr6":0,"D1":0,"D2":0, "gpus":[{"hash":31.151, "temp":"56", "fan":80},{"hash":31.035, "temp":"57", "fan":80},{"hash":31.125, "temp":"59", "fan":80},{"hash":31.144, "temp":"61", "fan":80},{"hash":31.138, "temp":"60", "fan":80},{"hash":31.139, "temp":"61", "fan":80},{"hash":31.122, "temp":"54", "fan":80},{"hash":31.150, "temp":"62", "fan":80},{"hash":31.105, "temp":"59", "fan":80},{"hash":31.134, "temp":"58", "fan":80},{"hash":31.143, "temp":"52", "fan":80},{"hash":31.136, "temp":"48", "fan":80},{"hash":31.141, "temp":"62", "fan":80}]},{ "miner":"Miner04", "MinerID":1027, "cards":13,"IPAddress":"10.0.1.139", "maxhash":382.8370, "hash":382.396,"Min30":0,"Hr2":0,"Hr6":0,"D1":0,"D2":0, "gpus":[{"hash":29.373, "temp":"57", "fan":83},{"hash":29.390, "temp":"71", "fan":83},{"hash":29.380, "temp":"56", "fan":83},{"hash":29.433, "temp":"61", "fan":83},{"hash":29.423, "temp":"59", "fan":83},{"hash":29.437, "temp":"55", "fan":83},{"hash":29.427, "temp":"61", "fan":83},{"hash":29.421, "temp":"63", "fan":83},{"hash":29.435, "temp":"59", "fan":83},{"hash":29.404, "temp":"69", "fan":83},{"hash":29.440, "temp":"61", "fan":83},{"hash":29.423, "temp":"58", "fan":83},{"hash":29.406, "temp":"58", "fan":83}]},{ "miner":"Miner05", "MinerID":1028, "cards":13,"IPAddress":"10.0.1.62", "maxhash":407.3160, "hash":405.085,"Min30":0,"Hr2":0,"Hr6":0,"D1":0,"D2":0, "gpus":[{"hash":31.157, "temp":"53", "fan":80},{"hash":31.133, "temp":"52", "fan":80},{"hash":31.140, "temp":"56", "fan":80},{"hash":31.137, "temp":"50", "fan":80},{"hash":31.322, "temp":"51", "fan":80},{"hash":31.331, "temp":"58", "fan":80},{"hash":31.152, "temp":"49", "fan":80},{"hash":31.332, "temp":"51", "fan":80},{"hash":31.150, "temp":"47", "fan":80},{"hash":31.148, "temp":"52", "fan":80},{"hash":30.796, "temp":"53", "fan":80},{"hash":31.142, "temp":"54", "fan":80},{"hash":31.140, "temp":"59", "fan":80}]},{ "miner":"Miner06", "MinerID":1029, "cards":12,"IPAddress":"10.0.1.140", "maxhash":380.8200, "hash":377.150,"Min30":0,"Hr2":0,"Hr6":0,"D1":0,"D2":0, "gpus":[{"hash":31.144, "temp":"55", "fan":83},{"hash":31.142, "temp":"53", "fan":83},{"hash":31.136, "temp":"58", "fan":83},{"hash":31.117, "temp":"62", "fan":83},{"hash":31.141, "temp":"59", "fan":83},{"hash":31.629, "temp":"51", "fan":83},{"hash":31.718, "temp":"48", "fan":83},{"hash":31.627, "temp":"48", "fan":83},{"hash":31.611, "temp":"53", "fan":83},{"hash":31.621, "temp":"54", "fan":83},{"hash":31.634, "temp":"51", "fan":83},{"hash":31.624, "temp":"60", "fan":83}]},{ "miner":"Miner07", "MinerID":1030, "cards":9,"IPAddress":"10.0.1.65", "maxhash":278.0460, "hash":304.207,"Min30":0,"Hr2":0,"Hr6":0,"D1":0,"D2":1, "gpus":[{"hash":30.266, "temp":"65", "fan":83},{"hash":30.311, "temp":"60", "fan":83},{"hash":30.890, "temp":"49", "fan":83},{"hash":30.831, "temp":"53", "fan":83},{"hash":30.311, "temp":"64", "fan":83},{"hash":30.313, "temp":"60", "fan":83},{"hash":30.320, "temp":"65", "fan":83},{"hash":30.327, "temp":"63", "fan":83},{"hash":30.309, "temp":"67", "fan":83},{"hash":30.323, "temp":"50", "fan":83}]}]}