{"MaxTotalHashRate":1982.0630,"CurrentTotalHashRate":1953.105,"LastUpdateDate":"Mar  5 2018  9:51PM","RIGs":9,"GPUs":65,"Miners":[{ "miner":"Miner1", "MinerID":1012, "cards":7,"IPAddress":"10.0.1.61", "maxhash":210.7910, "hash":203.409,"Min30":0,"Hr2":0,"Hr6":0,"D1":0,"D2":0, "gpus":[{"hash":28.723, "temp":"58", "fan":83},{"hash":28.721, "temp":"55", "fan":83},{"hash":28.723, "temp":"57", "fan":83},{"hash":29.040, "temp":"60", "fan":83},{"hash":29.371, "temp":"47", "fan":83},{"hash":30.106, "temp":"42", "fan":83},{"hash":28.721, "temp":"54", "fan":83}]},{ "miner":"Miner11", "MinerID":1020, "cards":7,"IPAddress":"10.0.1.37", "maxhash":209.7480, "hash":207.075,"Min30":0,"Hr2":0,"Hr6":0,"D1":0,"D2":0, "gpus":[{"hash":29.306, "temp":"53", "fan":83},{"hash":29.319, "temp":"53", "fan":83},{"hash":29.921, "temp":"48", "fan":83},{"hash":29.979, "temp":"50", "fan":83},{"hash":29.935, "temp":"52", "fan":83},{"hash":29.949, "temp":"58", "fan":83},{"hash":28.662, "temp":"47", "fan":83}]},{ "miner":"Miner12", "MinerID":1016, "cards":8,"IPAddress":"10.0.1.63", "maxhash":242.0240, "hash":240.998,"Min30":0,"Hr2":0,"Hr6":0,"D1":1,"D2":4, "gpus":[{"hash":30.055, "temp":"55", "fan":83},{"hash":30.057, "temp":"63", "fan":83},{"hash":30.052, "temp":"54", "fan":83},{"hash":30.064, "temp":"50", "fan":83},{"hash":30.331, "temp":"52", "fan":83},{"hash":30.055, "temp":"54", "fan":83},{"hash":30.056, "temp":"53", "fan":83},{"hash":30.325, "temp":"58", "fan":83}]},{ "miner":"Miner13", "MinerID":1021, "cards":8,"IPAddress":"10.0.1.5", "maxhash":240.4160, "hash":240.607,"Min30":0,"Hr2":0,"Hr6":0,"D1":0,"D2":1, "gpus":[{"hash":30.000, "temp":"60", "fan":83},{"hash":30.049, "temp":"59", "fan":83},{"hash":30.051, "temp":"60", "fan":83},{"hash":30.323, "temp":"55", "fan":83},{"hash":30.044, "temp":"52", "fan":83},{"hash":30.039, "temp":"57", "fan":83},{"hash":30.045, "temp":"54", "fan":83},{"hash":30.052, "temp":"60", "fan":83}]},{ "miner":"Miner14", "MinerID":1014, "cards":7,"IPAddress":"10.0.1.88", "maxhash":219.4360, "hash":210.732,"Min30":0,"Hr2":0,"Hr6":0,"D1":1,"D2":7, "gpus":[{"hash":31.323, "temp":"44", "fan":83},{"hash":29.019, "temp":"42", "fan":83},{"hash":30.001, "temp":"58", "fan":83},{"hash":30.032, "temp":"57", "fan":83},{"hash":29.033, "temp":"63", "fan":83},{"hash":31.342, "temp":"46", "fan":83},{"hash":29.978, "temp":"69", "fan":83}]},{ "miner":"Miner21", "MinerID":1017, "cards":8,"IPAddress":"10.0.1.50", "maxhash":240.3520, "hash":239.824,"Min30":0,"Hr2":0,"Hr6":0,"D1":0,"D2":0, "gpus":[{"hash":30.038, "temp":"68", "fan":83},{"hash":29.887, "temp":"57", "fan":83},{"hash":30.038, "temp":"53", "fan":83},{"hash":30.030, "temp":"57", "fan":83},{"hash":30.034, "temp":"62", "fan":83},{"hash":30.027, "temp":"71", "fan":83},{"hash":29.759, "temp":"70", "fan":83},{"hash":30.008, "temp":"61", "fan":83}]},{ "miner":"Miner22", "MinerID":1018, "cards":8,"IPAddress":"10.0.1.65", "maxhash":249.2320, "hash":248.445,"Min30":0,"Hr2":0,"Hr6":0,"D1":1,"D2":1, "gpus":[{"hash":31.158, "temp":"48", "fan":80},{"hash":30.911, "temp":"43", "fan":80},{"hash":31.144, "temp":"48", "fan":80},{"hash":30.911, "temp":"42", "fan":80},{"hash":31.149, "temp":"48", "fan":80},{"hash":31.141, "temp":"48", "fan":80},{"hash":31.124, "temp":"51", "fan":80},{"hash":30.904, "temp":"45", "fan":80}]},{ "miner":"Miner23", "MinerID":1022, "cards":8,"IPAddress":"10.0.1.113", "maxhash":250.0560, "hash":247.506,"Min30":0,"Hr2":0,"Hr6":0,"D1":0,"D2":0, "gpus":[{"hash":31.295, "temp":"48", "fan":80},{"hash":28.965, "temp":"62", "fan":80},{"hash":31.323, "temp":"52", "fan":80},{"hash":31.246, "temp":"51", "fan":80},{"hash":31.294, "temp":"53", "fan":80},{"hash":31.261, "temp":"51", "fan":80},{"hash":30.846, "temp":"49", "fan":80},{"hash":31.274, "temp":"53", "fan":80}]},{ "miner":"Miner24", "MinerID":1023, "cards":4,"IPAddress":"10.0.1.70", "maxhash":120.0080, "hash":114.509,"Min30":0,"Hr2":0,"Hr6":0,"D1":0,"D2":0, "gpus":[{"hash":28.058, "temp":"43", "fan":83},{"hash":29.053, "temp":"47", "fan":83},{"hash":30.042, "temp":"43", "fan":83},{"hash":27.354, "temp":"48", "fan":83}]}]}