{"MaxTotalHashRate":1983.4460,"CurrentTotalHashRate":1953.027,"LastUpdateDate":"Mar  4 2018  3:04AM","RIGs":9,"GPUs":65,"Miners":[{ "miner":"Miner1", "MinerID":1012, "cards":7,"IPAddress":"10.0.1.61", "maxhash":210.5670, "hash":203.679,"Min30":0,"Hr2":0,"Hr6":0,"D1":0,"D2":1, "gpus":[{"hash":28.764, "temp":"58", "fan":83},{"hash":28.766, "temp":"55", "fan":83},{"hash":28.760, "temp":"57", "fan":83},{"hash":29.074, "temp":"59", "fan":83},{"hash":29.418, "temp":"47", "fan":83},{"hash":30.141, "temp":"43", "fan":83},{"hash":28.754, "temp":"53", "fan":83}]},{ "miner":"Miner11", "MinerID":1020, "cards":7,"IPAddress":"10.0.1.37", "maxhash":209.6570, "hash":207.178,"Min30":0,"Hr2":0,"Hr6":0,"D1":0,"D2":0, "gpus":[{"hash":29.366, "temp":"53", "fan":83},{"hash":29.359, "temp":"46", "fan":83},{"hash":29.978, "temp":"45", "fan":83},{"hash":29.964, "temp":"50", "fan":83},{"hash":29.925, "temp":"46", "fan":83},{"hash":29.961, "temp":"64", "fan":83},{"hash":28.622, "temp":"46", "fan":83}]},{ "miner":"Miner12", "MinerID":1016, "cards":8,"IPAddress":"10.0.1.63", "maxhash":242.0960, "hash":240.415,"Min30":0,"Hr2":0,"Hr6":1,"D1":1,"D2":2, "gpus":[{"hash":29.976, "temp":"59", "fan":83},{"hash":29.971, "temp":"65", "fan":83},{"hash":29.953, "temp":"57", "fan":83},{"hash":29.993, "temp":"51", "fan":83},{"hash":30.282, "temp":"53", "fan":83},{"hash":30.002, "temp":"56", "fan":83},{"hash":29.983, "temp":"56", "fan":83},{"hash":30.253, "temp":"60", "fan":83}]},{ "miner":"Miner13", "MinerID":1021, "cards":8,"IPAddress":"10.0.1.5", "maxhash":242.5040, "hash":240.576,"Min30":0,"Hr2":0,"Hr6":0,"D1":0,"D2":0, "gpus":[{"hash":29.996, "temp":"60", "fan":83},{"hash":30.023, "temp":"58", "fan":83},{"hash":30.040, "temp":"57", "fan":83},{"hash":30.322, "temp":"54", "fan":83},{"hash":30.038, "temp":"54", "fan":83},{"hash":30.049, "temp":"56", "fan":83},{"hash":30.050, "temp":"54", "fan":83},{"hash":30.054, "temp":"59", "fan":83}]},{ "miner":"Miner14", "MinerID":1014, "cards":7,"IPAddress":"10.0.1.88", "maxhash":219.0300, "hash":210.413,"Min30":0,"Hr2":0,"Hr6":0,"D1":0,"D2":1, "gpus":[{"hash":31.345, "temp":"46", "fan":83},{"hash":28.962, "temp":"42", "fan":83},{"hash":29.972, "temp":"56", "fan":83},{"hash":29.972, "temp":"58", "fan":83},{"hash":28.954, "temp":"58", "fan":83},{"hash":31.216, "temp":"45", "fan":83},{"hash":29.988, "temp":"68", "fan":83}]},{ "miner":"Miner21", "MinerID":1017, "cards":8,"IPAddress":"10.0.1.50", "maxhash":240.3440, "hash":239.838,"Min30":0,"Hr2":0,"Hr6":0,"D1":0,"D2":0, "gpus":[{"hash":30.036, "temp":"65", "fan":83},{"hash":29.877, "temp":"56", "fan":83},{"hash":30.033, "temp":"52", "fan":83},{"hash":30.025, "temp":"57", "fan":83},{"hash":30.033, "temp":"63", "fan":83},{"hash":30.038, "temp":"68", "fan":83},{"hash":29.759, "temp":"67", "fan":83},{"hash":30.033, "temp":"63", "fan":83}]},{ "miner":"Miner22", "MinerID":1018, "cards":8,"IPAddress":"10.0.1.65", "maxhash":249.1680, "hash":248.473,"Min30":0,"Hr2":0,"Hr6":0,"D1":0,"D2":1, "gpus":[{"hash":31.153, "temp":"51", "fan":80},{"hash":30.921, "temp":"48", "fan":80},{"hash":31.133, "temp":"51", "fan":80},{"hash":30.918, "temp":"42", "fan":80},{"hash":31.154, "temp":"49", "fan":80},{"hash":31.124, "temp":"53", "fan":80},{"hash":31.138, "temp":"50", "fan":80},{"hash":30.929, "temp":"46", "fan":80}]},{ "miner":"Miner23", "MinerID":1022, "cards":8,"IPAddress":"10.0.1.113", "maxhash":250.2160, "hash":247.824,"Min30":0,"Hr2":0,"Hr6":0,"D1":0,"D2":0, "gpus":[{"hash":31.267, "temp":"49", "fan":80},{"hash":28.987, "temp":"61", "fan":80},{"hash":31.239, "temp":"49", "fan":80},{"hash":31.223, "temp":"51", "fan":80},{"hash":31.306, "temp":"53", "fan":80},{"hash":31.271, "temp":"53", "fan":80},{"hash":31.253, "temp":"50", "fan":80},{"hash":31.275, "temp":"52", "fan":80}]},{ "miner":"Miner24", "MinerID":1023, "cards":4,"IPAddress":"10.0.1.70", "maxhash":119.8640, "hash":114.631,"Min30":0,"Hr2":0,"Hr6":0,"D1":0,"D2":1, "gpus":[{"hash":28.317, "temp":"43", "fan":83},{"hash":28.981, "temp":"47", "fan":83},{"hash":29.965, "temp":"43", "fan":83},{"hash":27.367, "temp":"48", "fan":83}]}]}