{"MaxTotalHashRate":2733.4230,"CurrentTotalHashRate":2671.663,"LastUpdateDate":"Jun 25 2018  9:25PM","RIGs":7,"GPUs":89,"Miners":[{ "miner":"Miner01", "MinerID":1024, "cards":13,"IPAddress":"10.0.1.137", "maxhash":391.2610, "hash":384.184,"Min30":0,"Hr2":0,"Hr6":0,"D1":0,"D2":0, "gpus":[{"hash":30.076, "temp":"64", "fan":83},{"hash":29.846, "temp":"71", "fan":83},{"hash":29.717, "temp":"63", "fan":83},{"hash":26.373, "temp":"74", "fan":83},{"hash":30.087, "temp":"63", "fan":83},{"hash":30.084, "temp":"67", "fan":83},{"hash":28.889, "temp":"62", "fan":83},{"hash":30.088, "temp":"75", "fan":83},{"hash":30.089, "temp":"62", "fan":83},{"hash":29.742, "temp":"62", "fan":83},{"hash":29.737, "temp":"70", "fan":83},{"hash":29.735, "temp":"72", "fan":83},{"hash":29.714, "temp":"69", "fan":83}]},{ "miner":"Miner02", "MinerID":1025, "cards":13,"IPAddress":"10.0.1.138", "maxhash":390.8450, "hash":383.245,"Min30":0,"Hr2":0,"Hr6":0,"D1":0,"D2":0, "gpus":[{"hash":29.989, "temp":"67", "fan":83},{"hash":29.162, "temp":"61", "fan":83},{"hash":30.073, "temp":"68", "fan":83},{"hash":30.075, "temp":"64", "fan":83},{"hash":29.684, "temp":"64", "fan":83},{"hash":30.066, "temp":"56", "fan":83},{"hash":29.771, "temp":"48", "fan":83},{"hash":29.256, "temp":"58", "fan":83},{"hash":28.020, "temp":"45", "fan":83},{"hash":29.386, "temp":"59", "fan":83},{"hash":29.238, "temp":"51", "fan":83},{"hash":29.257, "temp":"57", "fan":83},{"hash":29.264, "temp":"47", "fan":83}]},{ "miner":"Miner03", "MinerID":1026, "cards":13,"IPAddress":"10.0.1.76", "maxhash":404.9500, "hash":404.437,"Min30":0,"Hr2":0,"Hr6":0,"D1":0,"D2":1, "gpus":[{"hash":31.112, "temp":"61", "fan":80},{"hash":31.059, "temp":"61", "fan":80},{"hash":31.102, "temp":"61", "fan":80},{"hash":31.116, "temp":"63", "fan":80},{"hash":31.135, "temp":"64", "fan":80},{"hash":31.136, "temp":"64", "fan":80},{"hash":31.108, "temp":"60", "fan":80},{"hash":31.132, "temp":"55", "fan":80},{"hash":31.059, "temp":"52", "fan":80},{"hash":31.122, "temp":"60", "fan":80},{"hash":31.118, "temp":"58", "fan":80},{"hash":31.101, "temp":"53", "fan":80},{"hash":31.133, "temp":"59", "fan":80}]},{ "miner":"Miner04", "MinerID":1027, "cards":13,"IPAddress":"10.0.1.139", "maxhash":394.2640, "hash":390.251,"Min30":0,"Hr2":0,"Hr6":0,"D1":0,"D2":1, "gpus":[{"hash":29.962, "temp":"60", "fan":83},{"hash":30.146, "temp":"73", "fan":83},{"hash":30.337, "temp":"60", "fan":83},{"hash":29.959, "temp":"63", "fan":83},{"hash":29.426, "temp":"64", "fan":83},{"hash":30.329, "temp":"60", "fan":83},{"hash":29.235, "temp":"65", "fan":83},{"hash":29.971, "temp":"67", "fan":83},{"hash":29.973, "temp":"64", "fan":83},{"hash":29.985, "temp":"70", "fan":83},{"hash":30.301, "temp":"64", "fan":83},{"hash":30.321, "temp":"61", "fan":83},{"hash":30.299, "temp":"61", "fan":83}]},{ "miner":"Miner05", "MinerID":1028, "cards":13,"IPAddress":"10.0.1.62", "maxhash":405.0670, "hash":402.926,"Min30":0,"Hr2":1,"Hr6":1,"D1":2,"D2":4, "gpus":[{"hash":31.116, "temp":"53", "fan":80},{"hash":31.109, "temp":"57", "fan":80},{"hash":31.070, "temp":"63", "fan":80},{"hash":30.967, "temp":"60", "fan":80},{"hash":31.096, "temp":"63", "fan":80},{"hash":31.150, "temp":"61", "fan":80},{"hash":31.068, "temp":"52", "fan":80},{"hash":30.789, "temp":"63", "fan":80},{"hash":31.085, "temp":"65", "fan":80},{"hash":31.124, "temp":"57", "fan":80},{"hash":30.616, "temp":"58", "fan":80},{"hash":31.123, "temp":"60", "fan":80},{"hash":30.607, "temp":"66", "fan":80}]},{ "miner":"Miner06", "MinerID":1029, "cards":12,"IPAddress":"10.0.1.140", "maxhash":380.6520, "hash":375.302,"Min30":0,"Hr2":0,"Hr6":0,"D1":3,"D2":4, "gpus":[{"hash":31.114, "temp":"60", "fan":83},{"hash":31.091, "temp":"58", "fan":83},{"hash":31.128, "temp":"62", "fan":83},{"hash":31.122, "temp":"67", "fan":83},{"hash":31.091, "temp":"61", "fan":83},{"hash":31.439, "temp":"56", "fan":83},{"hash":31.744, "temp":"52", "fan":83},{"hash":30.789, "temp":"54", "fan":83},{"hash":31.445, "temp":"56", "fan":83},{"hash":31.430, "temp":"55", "fan":83},{"hash":31.459, "temp":"55", "fan":83},{"hash":31.444, "temp":"66", "fan":83}]},{ "miner":"Miner07", "MinerID":1030, "cards":12,"IPAddress":"10.0.1.65", "maxhash":366.3840, "hash":331.318,"Min30":0,"Hr2":1,"Hr6":5,"D1":7,"D2":7, "gpus":[{"hash":30.278, "temp":"68", "fan":83},{"hash":30.151, "temp":"66", "fan":83},{"hash":29.988, "temp":"72", "fan":83},{"hash":29.984, "temp":"71", "fan":83},{"hash":30.164, "temp":"73", "fan":83},{"hash":30.000, "temp":"71", "fan":83},{"hash":30.532, "temp":"57", "fan":83},{"hash":30.467, "temp":"65", "fan":83},{"hash":29.980, "temp":"70", "fan":83},{"hash":29.636, "temp":"56", "fan":83},{"hash":30.134, "temp":"71", "fan":83}]}]}