{"MaxTotalHashRate":1983.6480,"CurrentTotalHashRate":1941.922,"LastUpdateDate":"Mar  4 2018  7:23AM","RIGs":9,"GPUs":65,"Miners":[{ "miner":"Miner1", "MinerID":1012, "cards":7,"IPAddress":"10.0.1.61", "maxhash":210.8120, "hash":195.061,"Min30":0,"Hr2":0,"Hr6":0,"D1":0,"D2":1, "gpus":[{"hash":28.739, "temp":"58", "fan":83},{"hash":28.726, "temp":"55", "fan":83},{"hash":28.728, "temp":"57", "fan":83},{"hash":29.045, "temp":"59", "fan":83},{"hash":29.374, "temp":"48", "fan":83},{"hash":30.103, "temp":"43", "fan":83},{"hash":20.342, "temp":"54", "fan":83}]},{ "miner":"Miner11", "MinerID":1020, "cards":7,"IPAddress":"10.0.1.37", "maxhash":209.5940, "hash":207.041,"Min30":0,"Hr2":0,"Hr6":0,"D1":0,"D2":0, "gpus":[{"hash":29.314, "temp":"54", "fan":83},{"hash":29.342, "temp":"47", "fan":83},{"hash":29.946, "temp":"45", "fan":83},{"hash":29.929, "temp":"51", "fan":83},{"hash":29.927, "temp":"47", "fan":83},{"hash":29.931, "temp":"64", "fan":83},{"hash":28.648, "temp":"46", "fan":83}]},{ "miner":"Miner12", "MinerID":1016, "cards":8,"IPAddress":"10.0.1.63", "maxhash":241.9840, "hash":240.394,"Min30":0,"Hr2":0,"Hr6":0,"D1":1,"D2":2, "gpus":[{"hash":29.980, "temp":"59", "fan":83},{"hash":29.978, "temp":"65", "fan":83},{"hash":29.975, "temp":"57", "fan":83},{"hash":29.979, "temp":"51", "fan":83},{"hash":30.257, "temp":"53", "fan":83},{"hash":29.981, "temp":"57", "fan":83},{"hash":29.986, "temp":"56", "fan":83},{"hash":30.255, "temp":"60", "fan":83}]},{ "miner":"Miner13", "MinerID":1021, "cards":8,"IPAddress":"10.0.1.5", "maxhash":242.4960, "hash":240.594,"Min30":0,"Hr2":0,"Hr6":0,"D1":0,"D2":0, "gpus":[{"hash":29.997, "temp":"60", "fan":83},{"hash":30.052, "temp":"58", "fan":83},{"hash":30.043, "temp":"58", "fan":83},{"hash":30.312, "temp":"54", "fan":83},{"hash":30.051, "temp":"54", "fan":83},{"hash":30.042, "temp":"56", "fan":83},{"hash":30.052, "temp":"54", "fan":83},{"hash":30.041, "temp":"60", "fan":83}]},{ "miner":"Miner14", "MinerID":1014, "cards":7,"IPAddress":"10.0.1.88", "maxhash":218.9740, "hash":210.462,"Min30":0,"Hr2":0,"Hr6":0,"D1":0,"D2":1, "gpus":[{"hash":31.292, "temp":"46", "fan":83},{"hash":28.993, "temp":"42", "fan":83},{"hash":29.954, "temp":"57", "fan":83},{"hash":29.968, "temp":"58", "fan":83},{"hash":28.972, "temp":"59", "fan":83},{"hash":31.303, "temp":"45", "fan":83},{"hash":29.978, "temp":"68", "fan":83}]},{ "miner":"Miner21", "MinerID":1017, "cards":8,"IPAddress":"10.0.1.50", "maxhash":240.3440, "hash":238.520,"Min30":0,"Hr2":0,"Hr6":0,"D1":0,"D2":0, "gpus":[{"hash":30.036, "temp":"64", "fan":83},{"hash":28.570, "temp":"56", "fan":83},{"hash":30.035, "temp":"52", "fan":83},{"hash":30.024, "temp":"57", "fan":83},{"hash":30.033, "temp":"63", "fan":83},{"hash":30.030, "temp":"68", "fan":83},{"hash":29.758, "temp":"67", "fan":83},{"hash":30.031, "temp":"63", "fan":83}]},{ "miner":"Miner22", "MinerID":1018, "cards":8,"IPAddress":"10.0.1.65", "maxhash":249.4560, "hash":248.610,"Min30":0,"Hr2":0,"Hr6":0,"D1":0,"D2":1, "gpus":[{"hash":31.156, "temp":"51", "fan":80},{"hash":30.930, "temp":"49", "fan":80},{"hash":31.156, "temp":"52", "fan":80},{"hash":30.915, "temp":"43", "fan":80},{"hash":31.182, "temp":"49", "fan":80},{"hash":31.181, "temp":"55", "fan":80},{"hash":31.152, "temp":"51", "fan":80},{"hash":30.935, "temp":"47", "fan":80}]},{ "miner":"Miner23", "MinerID":1022, "cards":8,"IPAddress":"10.0.1.113", "maxhash":250.1120, "hash":247.775,"Min30":0,"Hr2":0,"Hr6":0,"D1":0,"D2":0, "gpus":[{"hash":31.260, "temp":"51", "fan":80},{"hash":28.974, "temp":"64", "fan":80},{"hash":31.273, "temp":"50", "fan":80},{"hash":31.259, "temp":"53", "fan":80},{"hash":31.250, "temp":"55", "fan":80},{"hash":31.264, "temp":"55", "fan":80},{"hash":31.261, "temp":"53", "fan":80},{"hash":31.230, "temp":"54", "fan":80}]},{ "miner":"Miner24", "MinerID":1023, "cards":4,"IPAddress":"10.0.1.70", "maxhash":119.8760, "hash":113.465,"Min30":0,"Hr2":0,"Hr6":0,"D1":0,"D2":1, "gpus":[{"hash":27.667, "temp":"44", "fan":83},{"hash":28.997, "temp":"48", "fan":83},{"hash":29.954, "temp":"44", "fan":83},{"hash":26.845, "temp":"50", "fan":83}]}]}