{"MaxTotalHashRate":2677.8850,"CurrentTotalHashRate":2620.849,"LastUpdateDate":"May 28 2018  6:10PM","RIGs":7,"GPUs":87,"Miners":[{ "miner":"Miner01", "MinerID":1024, "cards":13,"IPAddress":"10.0.1.137", "maxhash":391.2740, "hash":358.664,"Min30":0,"Hr2":0,"Hr6":0,"D1":0,"D2":1, "gpus":[{"hash":30.096, "temp":"66", "fan":100},{"hash":15.690, "temp":"83", "fan":100},{"hash":29.745, "temp":"63", "fan":100},{"hash":13.986, "temp":"74", "fan":100},{"hash":30.096, "temp":"62", "fan":100},{"hash":30.092, "temp":"66", "fan":100},{"hash":29.824, "temp":"69", "fan":100},{"hash":30.098, "temp":"73", "fan":100},{"hash":30.098, "temp":"59", "fan":100},{"hash":29.721, "temp":"60", "fan":100},{"hash":29.737, "temp":"64", "fan":100},{"hash":29.736, "temp":"60", "fan":100},{"hash":29.738, "temp":"69", "fan":100}]},{ "miner":"Miner02", "MinerID":1025, "cards":13,"IPAddress":"10.0.1.138", "maxhash":390.9620, "hash":383.518,"Min30":0,"Hr2":0,"Hr6":0,"D1":0,"D2":0, "gpus":[{"hash":30.046, "temp":"65", "fan":83},{"hash":29.168, "temp":"59", "fan":83},{"hash":30.076, "temp":"68", "fan":83},{"hash":30.071, "temp":"63", "fan":83},{"hash":29.672, "temp":"65", "fan":83},{"hash":30.068, "temp":"56", "fan":83},{"hash":29.994, "temp":"47", "fan":83},{"hash":29.246, "temp":"59", "fan":83},{"hash":28.039, "temp":"45", "fan":83},{"hash":29.389, "temp":"59", "fan":83},{"hash":29.244, "temp":"51", "fan":83},{"hash":29.254, "temp":"59", "fan":83},{"hash":29.245, "temp":"46", "fan":83}]},{ "miner":"Miner03", "MinerID":1026, "cards":13,"IPAddress":"10.0.1.76", "maxhash":405.3400, "hash":405.038,"Min30":0,"Hr2":0,"Hr6":0,"D1":0,"D2":0, "gpus":[{"hash":31.124, "temp":"63", "fan":80},{"hash":31.087, "temp":"64", "fan":80},{"hash":31.177, "temp":"65", "fan":80},{"hash":31.174, "temp":"68", "fan":80},{"hash":31.140, "temp":"64", "fan":80},{"hash":31.157, "temp":"67", "fan":80},{"hash":31.178, "temp":"61", "fan":80},{"hash":31.164, "temp":"57", "fan":80},{"hash":31.175, "temp":"54", "fan":80},{"hash":31.160, "temp":"63", "fan":80},{"hash":31.176, "temp":"58", "fan":80},{"hash":31.156, "temp":"54", "fan":80},{"hash":31.164, "temp":"60", "fan":80}]},{ "miner":"Miner04", "MinerID":1027, "cards":13,"IPAddress":"10.0.1.139", "maxhash":394.2380, "hash":390.831,"Min30":0,"Hr2":0,"Hr6":0,"D1":0,"D2":0, "gpus":[{"hash":29.966, "temp":"63", "fan":83},{"hash":30.325, "temp":"75", "fan":83},{"hash":30.340, "temp":"61", "fan":83},{"hash":29.982, "temp":"64", "fan":83},{"hash":29.792, "temp":"65", "fan":83},{"hash":30.322, "temp":"61", "fan":83},{"hash":29.248, "temp":"67", "fan":83},{"hash":29.974, "temp":"67", "fan":83},{"hash":29.966, "temp":"65", "fan":83},{"hash":29.974, "temp":"72", "fan":83},{"hash":30.313, "temp":"65", "fan":83},{"hash":30.322, "temp":"62", "fan":83},{"hash":30.301, "temp":"62", "fan":83}]},{ "miner":"Miner05", "MinerID":1028, "cards":13,"IPAddress":"10.0.1.62", "maxhash":405.7950, "hash":404.032,"Min30":0,"Hr2":0,"Hr6":0,"D1":0,"D2":0, "gpus":[{"hash":31.137, "temp":"60", "fan":80},{"hash":31.120, "temp":"62", "fan":80},{"hash":31.134, "temp":"66", "fan":80},{"hash":31.140, "temp":"60", "fan":80},{"hash":31.202, "temp":"59", "fan":80},{"hash":31.023, "temp":"64", "fan":80},{"hash":31.128, "temp":"54", "fan":80},{"hash":31.158, "temp":"58", "fan":80},{"hash":31.129, "temp":"56", "fan":80},{"hash":31.126, "temp":"59", "fan":80},{"hash":30.454, "temp":"62", "fan":80},{"hash":31.143, "temp":"62", "fan":80},{"hash":31.133, "temp":"64", "fan":80}]},{ "miner":"Miner06", "MinerID":1029, "cards":12,"IPAddress":"10.0.1.140", "maxhash":381.1560, "hash":375.528,"Min30":0,"Hr2":0,"Hr6":0,"D1":0,"D2":1, "gpus":[{"hash":31.132, "temp":"63", "fan":83},{"hash":31.143, "temp":"59", "fan":83},{"hash":31.130, "temp":"65", "fan":83},{"hash":31.129, "temp":"71", "fan":83},{"hash":31.142, "temp":"66", "fan":83},{"hash":31.451, "temp":"56", "fan":83},{"hash":31.753, "temp":"53", "fan":83},{"hash":30.798, "temp":"53", "fan":83},{"hash":31.451, "temp":"60", "fan":83},{"hash":31.480, "temp":"59", "fan":83},{"hash":31.456, "temp":"55", "fan":83},{"hash":31.457, "temp":"67", "fan":83}]},{ "miner":"Miner07", "MinerID":1030, "cards":10,"IPAddress":"10.0.1.65", "maxhash":309.1200, "hash":303.238,"Min30":0,"Hr2":0,"Hr6":0,"D1":0,"D2":1, "gpus":[{"hash":30.264, "temp":"70", "fan":83},{"hash":30.333, "temp":"63", "fan":83},{"hash":30.888, "temp":"52", "fan":83},{"hash":30.466, "temp":"58", "fan":83},{"hash":30.232, "temp":"68", "fan":83},{"hash":30.234, "temp":"65", "fan":83},{"hash":30.149, "temp":"70", "fan":83},{"hash":30.171, "temp":"66", "fan":83},{"hash":30.166, "temp":"69", "fan":83},{"hash":30.330, "temp":"54", "fan":83}]}]}