{"MaxTotalHashRate":2552.7530,"CurrentTotalHashRate":2268.538,"LastUpdateDate":"Apr 16 2018 11:55AM","RIGs":7,"GPUs":85,"Miners":[{ "miner":"Row1", "MinerID":1024, "cards":13,"IPAddress":"10.0.1.137", "maxhash":391.1180, "hash":388.577,"Min30":0,"Hr2":0,"Hr6":1,"D1":1,"D2":1, "gpus":[{"hash":30.076, "temp":"53", "fan":83},{"hash":30.088, "temp":"70", "fan":83},{"hash":30.090, "temp":"50", "fan":83},{"hash":30.077, "temp":"63", "fan":83},{"hash":30.079, "temp":"56", "fan":83},{"hash":30.081, "temp":"65", "fan":83},{"hash":27.612, "temp":"60", "fan":83},{"hash":30.075, "temp":"66", "fan":83},{"hash":30.090, "temp":"59", "fan":83},{"hash":30.057, "temp":"59", "fan":83},{"hash":30.082, "temp":"53", "fan":83},{"hash":30.075, "temp":"57", "fan":83},{"hash":30.090, "temp":"61", "fan":83}]},{ "miner":"Row2", "MinerID":1025, "cards":12,"IPAddress":"10.0.1.138", "maxhash":363.4200, "hash":345.921,"Min30":0,"Hr2":2,"Hr6":2,"D1":2,"D2":2, "gpus":[{"hash":30.009, "temp":"53", "fan":83},{"hash":30.199, "temp":"55", "fan":83},{"hash":30.057, "temp":"61", "fan":83},{"hash":30.065, "temp":"60", "fan":83},{"hash":26.003, "temp":"62", "fan":83},{"hash":30.041, "temp":"54", "fan":83},{"hash":30.232, "temp":"38", "fan":83},{"hash":29.158, "temp":"42", "fan":83},{"hash":26.544, "temp":"55", "fan":83},{"hash":30.276, "temp":"41", "fan":83},{"hash":29.323, "temp":"53", "fan":83},{"hash":24.007, "temp":"45", "fan":83}]},{ "miner":"Row3", "MinerID":1026, "cards":13,"IPAddress":"10.0.1.76", "maxhash":413.1790, "hash":411.035,"Min30":0,"Hr2":0,"Hr6":0,"D1":0,"D2":0, "gpus":[{"hash":31.732, "temp":"51", "fan":80},{"hash":31.742, "temp":"49", "fan":80},{"hash":31.137, "temp":"52", "fan":80},{"hash":31.757, "temp":"52", "fan":80},{"hash":31.122, "temp":"51", "fan":80},{"hash":31.121, "temp":"49", "fan":80},{"hash":31.775, "temp":"51", "fan":80},{"hash":31.773, "temp":"54", "fan":80},{"hash":31.771, "temp":"54", "fan":80},{"hash":31.793, "temp":"49", "fan":80},{"hash":31.778, "temp":"49", "fan":80},{"hash":31.778, "temp":"45", "fan":80},{"hash":31.750, "temp":"55", "fan":80}]},{ "miner":"Row4", "MinerID":1027, "cards":13,"IPAddress":"10.0.1.139", "maxhash":394.1990, "hash":150.907,"Min30":1,"Hr2":1,"Hr6":1,"D1":1,"D2":1, "gpus":[{"hash":30.280, "temp":"50", "fan":83},{"hash":30.333, "temp":"64", "fan":83},{"hash":29.835, "temp":"47", "fan":83},{"hash":30.247, "temp":"53", "fan":83},{"hash":30.209, "temp":"49", "fan":83},{"hash":0.000, "temp":"46", "fan":83},{"hash":0.000, "temp":"31", "fan":83},{"hash":0.000, "temp":"39", "fan":83},{"hash":0.000, "temp":"40", "fan":83},{"hash":0.000, "temp":"36", "fan":83},{"hash":0.000, "temp":"31", "fan":83},{"hash":0.000, "temp":"33", "fan":83},{"hash":0.000, "temp":"34", "fan":83}]},{ "miner":"Row5", "MinerID":1028, "cards":13,"IPAddress":"10.0.1.62", "maxhash":379.8600, "hash":370.863,"Min30":0,"Hr2":0,"Hr6":0,"D1":0,"D2":0, "gpus":[{"hash":28.282, "temp":"53", "fan":80},{"hash":28.309, "temp":"48", "fan":80},{"hash":28.327, "temp":"54", "fan":80},{"hash":28.337, "temp":"57", "fan":80},{"hash":29.225, "temp":"61", "fan":80},{"hash":29.209, "temp":"65", "fan":80},{"hash":28.329, "temp":"42", "fan":80},{"hash":29.224, "temp":"62", "fan":80},{"hash":28.333, "temp":"65", "fan":80},{"hash":28.328, "temp":"51", "fan":80},{"hash":28.303, "temp":"54", "fan":80},{"hash":28.333, "temp":"57", "fan":80},{"hash":28.319, "temp":"58", "fan":80}]},{ "miner":"Row6", "MinerID":1029, "cards":12,"IPAddress":"10.0.1.140", "maxhash":339.9960, "hash":339.506,"Min30":0,"Hr2":0,"Hr6":0,"D1":0,"D2":0, "gpus":[{"hash":28.289, "temp":"57", "fan":83},{"hash":28.326, "temp":"53", "fan":83},{"hash":28.300, "temp":"57", "fan":83},{"hash":28.311, "temp":"62", "fan":83},{"hash":28.319, "temp":"61", "fan":83},{"hash":28.051, "temp":"42", "fan":83},{"hash":28.306, "temp":"63", "fan":83},{"hash":28.311, "temp":"64", "fan":83},{"hash":28.321, "temp":"59", "fan":83},{"hash":28.331, "temp":"57", "fan":83},{"hash":28.318, "temp":"58", "fan":83},{"hash":28.314, "temp":"57", "fan":83}]},{ "miner":"Row7", "MinerID":1030, "cards":9,"IPAddress":"10.0.1.88", "maxhash":270.9810, "hash":261.729,"Min30":0,"Hr2":0,"Hr6":0,"D1":0,"D2":0, "gpus":[{"hash":29.891, "temp":"65", "fan":83},{"hash":29.953, "temp":"60", "fan":83},{"hash":26.410, "temp":"46", "fan":83},{"hash":30.111, "temp":"49", "fan":83},{"hash":29.976, "temp":"67", "fan":83},{"hash":29.980, "temp":"63", "fan":83},{"hash":29.977, "temp":"62", "fan":83},{"hash":29.974, "temp":"61", "fan":83},{"hash":25.453, "temp":"48", "fan":83}]}]}