{"MaxTotalHashRate":1984.4370,"CurrentTotalHashRate":1958.748,"LastUpdateDate":"Feb 21 2018 11:18PM","RIGs":9,"GPUs":65,"Miners":[{ "miner":"Miner1", "MinerID":1012, "cards":7,"IPAddress":"10.0.1.61", "maxhash":212.0720, "hash":207.493,"Min30":0,"Hr2":0,"Hr6":1,"D1":4,"D2":12, "gpus":[{"hash":29.420, "temp":"57", "fan":83},{"hash":29.425, "temp":"54", "fan":83},{"hash":29.431, "temp":"56", "fan":83},{"hash":30.302, "temp":"58", "fan":83},{"hash":29.367, "temp":"46", "fan":83},{"hash":30.110, "temp":"42", "fan":83},{"hash":29.436, "temp":"53", "fan":83}]},{ "miner":"Miner11", "MinerID":1020, "cards":7,"IPAddress":"10.0.1.37", "maxhash":209.8670, "hash":207.315,"Min30":0,"Hr2":0,"Hr6":0,"D1":0,"D2":1, "gpus":[{"hash":29.381, "temp":"53", "fan":83},{"hash":29.381, "temp":"45", "fan":83},{"hash":29.978, "temp":"43", "fan":83},{"hash":29.947, "temp":"49", "fan":83},{"hash":29.976, "temp":"45", "fan":83},{"hash":29.961, "temp":"64", "fan":83},{"hash":28.687, "temp":"44", "fan":83}]},{ "miner":"Miner12", "MinerID":1016, "cards":8,"IPAddress":"10.0.1.63", "maxhash":241.9840, "hash":240.416,"Min30":0,"Hr2":0,"Hr6":0,"D1":1,"D2":2, "gpus":[{"hash":29.982, "temp":"58", "fan":83},{"hash":29.975, "temp":"64", "fan":83},{"hash":30.005, "temp":"56", "fan":83},{"hash":30.006, "temp":"50", "fan":83},{"hash":30.240, "temp":"52", "fan":83},{"hash":29.978, "temp":"56", "fan":83},{"hash":29.951, "temp":"55", "fan":83},{"hash":30.276, "temp":"59", "fan":83}]},{ "miner":"Miner13", "MinerID":1021, "cards":8,"IPAddress":"10.0.1.5", "maxhash":241.8960, "hash":239.997,"Min30":0,"Hr2":0,"Hr6":0,"D1":0,"D2":2, "gpus":[{"hash":29.928, "temp":"59", "fan":83},{"hash":29.971, "temp":"57", "fan":83},{"hash":29.983, "temp":"57", "fan":83},{"hash":30.240, "temp":"53", "fan":83},{"hash":29.968, "temp":"52", "fan":83},{"hash":29.969, "temp":"56", "fan":83},{"hash":29.968, "temp":"52", "fan":83},{"hash":29.968, "temp":"58", "fan":83}]},{ "miner":"Miner14", "MinerID":1014, "cards":7,"IPAddress":"10.0.1.88", "maxhash":219.1980, "hash":210.531,"Min30":0,"Hr2":0,"Hr6":0,"D1":0,"D2":1, "gpus":[{"hash":31.310, "temp":"44", "fan":83},{"hash":28.982, "temp":"41", "fan":83},{"hash":29.978, "temp":"55", "fan":83},{"hash":29.984, "temp":"57", "fan":83},{"hash":28.980, "temp":"58", "fan":83},{"hash":31.316, "temp":"44", "fan":83},{"hash":29.978, "temp":"67", "fan":83}]},{ "miner":"Miner21", "MinerID":1017, "cards":8,"IPAddress":"10.0.1.50", "maxhash":240.0400, "hash":239.364,"Min30":0,"Hr2":0,"Hr6":0,"D1":2,"D2":4, "gpus":[{"hash":29.950, "temp":"63", "fan":83},{"hash":29.935, "temp":"54", "fan":83},{"hash":29.953, "temp":"51", "fan":83},{"hash":29.953, "temp":"56", "fan":83},{"hash":29.946, "temp":"61", "fan":83},{"hash":29.956, "temp":"66", "fan":83},{"hash":29.672, "temp":"67", "fan":83},{"hash":29.995, "temp":"61", "fan":83}]},{ "miner":"Miner22", "MinerID":1018, "cards":8,"IPAddress":"10.0.1.65", "maxhash":249.1360, "hash":248.423,"Min30":0,"Hr2":0,"Hr6":0,"D1":1,"D2":3, "gpus":[{"hash":31.134, "temp":"50", "fan":80},{"hash":30.926, "temp":"47", "fan":80},{"hash":31.129, "temp":"51", "fan":80},{"hash":30.910, "temp":"41", "fan":80},{"hash":31.120, "temp":"47", "fan":80},{"hash":31.141, "temp":"53", "fan":80},{"hash":31.139, "temp":"49", "fan":80},{"hash":30.919, "temp":"45", "fan":80}]},{ "miner":"Miner23", "MinerID":1022, "cards":8,"IPAddress":"10.0.1.113", "maxhash":250.2080, "hash":248.143,"Min30":0,"Hr2":0,"Hr6":0,"D1":0,"D2":0, "gpus":[{"hash":31.262, "temp":"48", "fan":80},{"hash":29.028, "temp":"65", "fan":80},{"hash":31.292, "temp":"49", "fan":80},{"hash":31.337, "temp":"51", "fan":80},{"hash":31.283, "temp":"52", "fan":80},{"hash":31.295, "temp":"52", "fan":80},{"hash":31.329, "temp":"50", "fan":80},{"hash":31.314, "temp":"52", "fan":80}]},{ "miner":"Miner24", "MinerID":1023, "cards":4,"IPAddress":"10.0.1.70", "maxhash":120.0360, "hash":117.066,"Min30":0,"Hr2":0,"Hr6":1,"D1":1,"D2":1, "gpus":[{"hash":29.316, "temp":"41", "fan":83},{"hash":28.982, "temp":"46", "fan":83},{"hash":29.980, "temp":"42", "fan":83},{"hash":28.787, "temp":"47", "fan":83}]}]}