{"MaxTotalHashRate":2613.6110,"CurrentTotalHashRate":2554.755,"LastUpdateDate":"Apr 19 2018  1:51AM","RIGs":7,"GPUs":85,"Miners":[{ "miner":"Row1", "MinerID":1024, "cards":13,"IPAddress":"10.0.1.137", "maxhash":390.9750, "hash":388.775,"Min30":0,"Hr2":0,"Hr6":2,"D1":0,"D2":10, "gpus":[{"hash":30.022, "temp":"52", "fan":83},{"hash":30.074, "temp":"64", "fan":83},{"hash":30.041, "temp":"52", "fan":83},{"hash":30.064, "temp":"62", "fan":83},{"hash":30.075, "temp":"64", "fan":83},{"hash":30.052, "temp":"60", "fan":83},{"hash":28.911, "temp":"60", "fan":83},{"hash":30.058, "temp":"71", "fan":83},{"hash":30.071, "temp":"59", "fan":83},{"hash":29.641, "temp":"55", "fan":83},{"hash":29.709, "temp":"56", "fan":83},{"hash":29.982, "temp":"48", "fan":83},{"hash":30.072, "temp":"66", "fan":83}]},{ "miner":"Row2", "MinerID":1025, "cards":12,"IPAddress":"10.0.1.138", "maxhash":364.1040, "hash":352.010,"Min30":0,"Hr2":0,"Hr6":0,"D1":0,"D2":1, "gpus":[{"hash":30.043, "temp":"52", "fan":83},{"hash":25.627, "temp":"52", "fan":83},{"hash":30.052, "temp":"57", "fan":83},{"hash":30.070, "temp":"56", "fan":83},{"hash":28.989, "temp":"62", "fan":83},{"hash":30.081, "temp":"52", "fan":83},{"hash":29.964, "temp":"38", "fan":83},{"hash":29.111, "temp":"40", "fan":83},{"hash":29.255, "temp":"55", "fan":83},{"hash":30.322, "temp":"41", "fan":83},{"hash":29.251, "temp":"49", "fan":83},{"hash":29.240, "temp":"43", "fan":83}]},{ "miner":"Row3", "MinerID":1026, "cards":13,"IPAddress":"10.0.1.76", "maxhash":404.9110, "hash":404.827,"Min30":0,"Hr2":0,"Hr6":0,"D1":0,"D2":0, "gpus":[{"hash":31.142, "temp":"53", "fan":80},{"hash":31.067, "temp":"55", "fan":80},{"hash":31.164, "temp":"56", "fan":80},{"hash":31.148, "temp":"58", "fan":80},{"hash":31.148, "temp":"60", "fan":80},{"hash":31.146, "temp":"59", "fan":80},{"hash":31.121, "temp":"51", "fan":80},{"hash":31.144, "temp":"67", "fan":80},{"hash":31.141, "temp":"64", "fan":80},{"hash":31.148, "temp":"55", "fan":80},{"hash":31.146, "temp":"48", "fan":80},{"hash":31.162, "temp":"45", "fan":80},{"hash":31.144, "temp":"63", "fan":80}]},{ "miner":"Row4", "MinerID":1027, "cards":13,"IPAddress":"10.0.1.139", "maxhash":382.8370, "hash":382.656,"Min30":0,"Hr2":0,"Hr6":0,"D1":0,"D2":0, "gpus":[{"hash":29.374, "temp":"58", "fan":83},{"hash":29.417, "temp":"69", "fan":83},{"hash":29.457, "temp":"58", "fan":83},{"hash":29.450, "temp":"63", "fan":83},{"hash":29.423, "temp":"65", "fan":83},{"hash":29.440, "temp":"61", "fan":83},{"hash":29.452, "temp":"57", "fan":83},{"hash":29.436, "temp":"67", "fan":83},{"hash":29.442, "temp":"67", "fan":83},{"hash":29.421, "temp":"70", "fan":83},{"hash":29.448, "temp":"63", "fan":83},{"hash":29.446, "temp":"60", "fan":83},{"hash":29.444, "temp":"61", "fan":83}]},{ "miner":"Row5", "MinerID":1028, "cards":13,"IPAddress":"10.0.1.62", "maxhash":411.7620, "hash":405.256,"Min30":0,"Hr2":0,"Hr6":1,"D1":0,"D2":2, "gpus":[{"hash":31.138, "temp":"57", "fan":80},{"hash":31.133, "temp":"54", "fan":80},{"hash":31.119, "temp":"60", "fan":80},{"hash":31.130, "temp":"54", "fan":80},{"hash":31.312, "temp":"57", "fan":80},{"hash":31.322, "temp":"62", "fan":80},{"hash":31.131, "temp":"46", "fan":80},{"hash":31.645, "temp":"57", "fan":80},{"hash":31.138, "temp":"52", "fan":80},{"hash":31.129, "temp":"52", "fan":80},{"hash":30.799, "temp":"59", "fan":80},{"hash":31.117, "temp":"60", "fan":80},{"hash":31.136, "temp":"62", "fan":80}]},{ "miner":"Row6", "MinerID":1029, "cards":12,"IPAddress":"10.0.1.140", "maxhash":381.6600, "hash":378.012,"Min30":0,"Hr2":0,"Hr6":0,"D1":0,"D2":4, "gpus":[{"hash":31.097, "temp":"58", "fan":83},{"hash":31.088, "temp":"54", "fan":83},{"hash":31.137, "temp":"61", "fan":83},{"hash":31.150, "temp":"62", "fan":83},{"hash":31.133, "temp":"60", "fan":83},{"hash":31.759, "temp":"70", "fan":83},{"hash":31.760, "temp":"45", "fan":83},{"hash":31.781, "temp":"65", "fan":83},{"hash":31.788, "temp":"62", "fan":83},{"hash":31.771, "temp":"67", "fan":83},{"hash":31.779, "temp":"66", "fan":83},{"hash":31.763, "temp":"63", "fan":83}]},{ "miner":"Row7", "MinerID":1030, "cards":9,"IPAddress":"10.0.1.65", "maxhash":277.3620, "hash":243.219,"Min30":0,"Hr2":0,"Hr6":0,"D1":0,"D2":13, "gpus":[{"hash":30.266, "temp":"66", "fan":83},{"hash":30.312, "temp":"61", "fan":83},{"hash":0.000, "temp":"36", "fan":83},{"hash":30.835, "temp":"51", "fan":83},{"hash":30.323, "temp":"66", "fan":83},{"hash":30.326, "temp":"63", "fan":83},{"hash":30.320, "temp":"64", "fan":83},{"hash":30.316, "temp":"69", "fan":83},{"hash":30.518, "temp":"51", "fan":83}]}]}