{"MaxTotalHashRate":1961.4780,"CurrentTotalHashRate":1925.018,"LastUpdateDate":"Feb 18 2018 10:09AM","Miners":[{ "miner":"Miner1", "MinerID":1012, "cards":8,"IPAddress":"10.0.1.61", "maxhash":246.3120, "hash":234.629,"Min30":0,"Hr2":0,"Hr6":0,"D1":0,"D2":0, "gpus":[{"hash":29.133, "temp":52, "fan":83},{"hash":28.924, "temp":57, "fan":83},{"hash":29.031, "temp":62, "fan":83},{"hash":29.049, "temp":58, "fan":83},{"hash":29.087, "temp":56, "fan":83},{"hash":30.138, "temp":50, "fan":83},{"hash":30.802, "temp":46, "fan":83},{"hash":28.463, "temp":54, "fan":83}]},{ "miner":"Miner11", "MinerID":1020, "cards":8,"IPAddress":"10.0.1.37", "maxhash":232.3440, "hash":224.612,"Min30":0,"Hr2":0,"Hr6":0,"D1":0,"D2":1, "gpus":[{"hash":28.124, "temp":53, "fan":83},{"hash":28.969, "temp":48, "fan":83},{"hash":22.509, "temp":46, "fan":83},{"hash":29.035, "temp":53, "fan":83},{"hash":29.004, "temp":63, "fan":83},{"hash":29.009, "temp":39, "fan":83},{"hash":28.997, "temp":45, "fan":83},{"hash":28.960, "temp":49, "fan":83}]},{ "miner":"Miner12", "MinerID":1016, "cards":8,"IPAddress":"10.0.1.63", "maxhash":242.0400, "hash":240.382,"Min30":0,"Hr2":1,"Hr6":3,"D1":4,"D2":7, "gpus":[{"hash":29.969, "temp":59, "fan":83},{"hash":29.988, "temp":66, "fan":83},{"hash":29.974, "temp":57, "fan":83},{"hash":29.983, "temp":51, "fan":83},{"hash":30.240, "temp":51, "fan":83},{"hash":29.984, "temp":58, "fan":83},{"hash":29.984, "temp":57, "fan":83},{"hash":30.256, "temp":60, "fan":83}]},{ "miner":"Miner13", "MinerID":1021, "cards":8,"IPAddress":"10.0.1.5", "maxhash":232.1200, "hash":231.854,"Min30":0,"Hr2":0,"Hr6":0,"D1":0,"D2":1, "gpus":[{"hash":28.978, "temp":59, "fan":83},{"hash":29.005, "temp":58, "fan":83},{"hash":28.988, "temp":58, "fan":83},{"hash":28.977, "temp":55, "fan":83},{"hash":28.976, "temp":50, "fan":83},{"hash":28.990, "temp":56, "fan":83},{"hash":28.968, "temp":52, "fan":83},{"hash":28.970, "temp":60, "fan":83}]},{ "miner":"Miner14", "MinerID":1014, "cards":7,"IPAddress":"10.0.1.88", "maxhash":219.3380, "hash":207.604,"Min30":0,"Hr2":0,"Hr6":0,"D1":0,"D2":0, "gpus":[{"hash":31.297, "temp":41, "fan":83},{"hash":29.005, "temp":40, "fan":83},{"hash":28.984, "temp":57, "fan":83},{"hash":29.005, "temp":53, "fan":83},{"hash":29.020, "temp":62, "fan":83},{"hash":31.310, "temp":44, "fan":83},{"hash":28.980, "temp":69, "fan":83}]},{ "miner":"Miner21", "MinerID":1017, "cards":8,"IPAddress":"10.0.1.50", "maxhash":232.2240, "hash":231.896,"Min30":0,"Hr2":0,"Hr6":0,"D1":0,"D2":0, "gpus":[{"hash":28.936, "temp":58, "fan":83},{"hash":28.963, "temp":53, "fan":83},{"hash":29.007, "temp":49, "fan":83},{"hash":28.991, "temp":55, "fan":83},{"hash":29.006, "temp":56, "fan":83},{"hash":28.993, "temp":63, "fan":83},{"hash":28.993, "temp":61, "fan":83},{"hash":29.003, "temp":59, "fan":83}]},{ "miner":"Miner22", "MinerID":1018, "cards":8,"IPAddress":"10.0.1.65", "maxhash":249.1760, "hash":248.429,"Min30":0,"Hr2":0,"Hr6":0,"D1":0,"D2":1, "gpus":[{"hash":31.139, "temp":53, "fan":80},{"hash":30.917, "temp":42, "fan":80},{"hash":31.128, "temp":50, "fan":80},{"hash":30.909, "temp":39, "fan":80},{"hash":31.143, "temp":52, "fan":80},{"hash":31.143, "temp":48, "fan":80},{"hash":31.130, "temp":53, "fan":80},{"hash":30.917, "temp":42, "fan":80}]},{ "miner":"Miner23", "MinerID":1022, "cards":8,"IPAddress":"10.0.1.113", "maxhash":250.0880, "hash":247.787,"Min30":0,"Hr2":0,"Hr6":0,"D1":0,"D2":1, "gpus":[{"hash":31.260, "temp":47, "fan":80},{"hash":29.002, "temp":56, "fan":80},{"hash":31.235, "temp":48, "fan":80},{"hash":31.260, "temp":49, "fan":80},{"hash":31.261, "temp":50, "fan":80},{"hash":31.257, "temp":49, "fan":80},{"hash":31.255, "temp":45, "fan":80},{"hash":31.254, "temp":51, "fan":80}]},{ "miner":"Miner24", "MinerID":1023, "cards":2,"IPAddress":"10.0.1.70", "maxhash":57.8360, "hash":57.825,"Min30":0,"Hr2":0,"Hr6":0,"D1":0,"D2":0, "gpus":[{"hash":28.914, "temp":40, "fan":83},{"hash":28.911, "temp":45, "fan":83}]}]}