{"MaxTotalHashRate":1984.2870,"CurrentTotalHashRate":1954.111,"LastUpdateDate":"Feb 24 2018 11:31AM","RIGs":9,"GPUs":65,"Miners":[{ "miner":"Miner1", "MinerID":1012, "cards":7,"IPAddress":"10.0.1.61", "maxhash":210.9870, "hash":203.425,"Min30":0,"Hr2":1,"Hr6":1,"D1":1,"D2":1, "gpus":[{"hash":28.728, "temp":"57", "fan":83},{"hash":28.722, "temp":"55", "fan":83},{"hash":28.724, "temp":"57", "fan":83},{"hash":29.053, "temp":"58", "fan":83},{"hash":29.362, "temp":"47", "fan":83},{"hash":30.100, "temp":"42", "fan":83},{"hash":28.733, "temp":"53", "fan":83}]},{ "miner":"Miner11", "MinerID":1020, "cards":7,"IPAddress":"10.0.1.37", "maxhash":209.6640, "hash":207.190,"Min30":0,"Hr2":0,"Hr6":0,"D1":0,"D2":0, "gpus":[{"hash":29.351, "temp":"55", "fan":83},{"hash":29.354, "temp":"49", "fan":83},{"hash":29.952, "temp":"48", "fan":83},{"hash":29.961, "temp":"51", "fan":83},{"hash":29.959, "temp":"48", "fan":83},{"hash":29.946, "temp":"68", "fan":83},{"hash":28.665, "temp":"50", "fan":83}]},{ "miner":"Miner12", "MinerID":1016, "cards":8,"IPAddress":"10.0.1.63", "maxhash":242.0080, "hash":240.546,"Min30":0,"Hr2":0,"Hr6":0,"D1":1,"D2":3, "gpus":[{"hash":30.005, "temp":"59", "fan":83},{"hash":30.012, "temp":"66", "fan":83},{"hash":30.009, "temp":"58", "fan":83},{"hash":29.975, "temp":"52", "fan":83},{"hash":30.270, "temp":"53", "fan":83},{"hash":30.027, "temp":"56", "fan":83},{"hash":29.978, "temp":"56", "fan":83},{"hash":30.267, "temp":"60", "fan":83}]},{ "miner":"Miner13", "MinerID":1021, "cards":8,"IPAddress":"10.0.1.5", "maxhash":242.5760, "hash":240.645,"Min30":0,"Hr2":0,"Hr6":0,"D1":0,"D2":0, "gpus":[{"hash":30.003, "temp":"60", "fan":83},{"hash":30.049, "temp":"58", "fan":83},{"hash":30.049, "temp":"58", "fan":83},{"hash":30.320, "temp":"55", "fan":83},{"hash":30.061, "temp":"54", "fan":83},{"hash":30.058, "temp":"57", "fan":83},{"hash":30.048, "temp":"54", "fan":83},{"hash":30.053, "temp":"60", "fan":83}]},{ "miner":"Miner14", "MinerID":1014, "cards":7,"IPAddress":"10.0.1.88", "maxhash":219.1280, "hash":210.512,"Min30":0,"Hr2":0,"Hr6":0,"D1":0,"D2":0, "gpus":[{"hash":31.299, "temp":"46", "fan":83},{"hash":28.988, "temp":"43", "fan":83},{"hash":29.987, "temp":"57", "fan":83},{"hash":29.975, "temp":"58", "fan":83},{"hash":28.977, "temp":"59", "fan":83},{"hash":31.306, "temp":"46", "fan":83},{"hash":29.976, "temp":"68", "fan":83}]},{ "miner":"Miner21", "MinerID":1017, "cards":8,"IPAddress":"10.0.1.50", "maxhash":240.3600, "hash":239.589,"Min30":0,"Hr2":0,"Hr6":0,"D1":0,"D2":0, "gpus":[{"hash":30.037, "temp":"65", "fan":83},{"hash":29.649, "temp":"58", "fan":83},{"hash":30.035, "temp":"52", "fan":83},{"hash":29.988, "temp":"58", "fan":83},{"hash":30.045, "temp":"64", "fan":83},{"hash":30.038, "temp":"70", "fan":83},{"hash":29.752, "temp":"69", "fan":83},{"hash":30.042, "temp":"64", "fan":83}]},{ "miner":"Miner22", "MinerID":1018, "cards":8,"IPAddress":"10.0.1.65", "maxhash":249.4400, "hash":248.427,"Min30":0,"Hr2":0,"Hr6":0,"D1":0,"D2":0, "gpus":[{"hash":31.121, "temp":"51", "fan":80},{"hash":30.907, "temp":"49", "fan":80},{"hash":31.126, "temp":"52", "fan":80},{"hash":30.931, "temp":"43", "fan":80},{"hash":31.130, "temp":"49", "fan":80},{"hash":31.147, "temp":"54", "fan":80},{"hash":31.148, "temp":"51", "fan":80},{"hash":30.912, "temp":"47", "fan":80}]},{ "miner":"Miner23", "MinerID":1022, "cards":8,"IPAddress":"10.0.1.113", "maxhash":250.2560, "hash":248.000,"Min30":0,"Hr2":0,"Hr6":0,"D1":0,"D2":0, "gpus":[{"hash":31.268, "temp":"49", "fan":80},{"hash":28.995, "temp":"61", "fan":80},{"hash":31.291, "temp":"49", "fan":80},{"hash":31.286, "temp":"52", "fan":80},{"hash":31.295, "temp":"54", "fan":80},{"hash":31.285, "temp":"53", "fan":80},{"hash":31.304, "temp":"50", "fan":80},{"hash":31.274, "temp":"53", "fan":80}]},{ "miner":"Miner24", "MinerID":1023, "cards":4,"IPAddress":"10.0.1.70", "maxhash":119.8680, "hash":115.777,"Min30":0,"Hr2":0,"Hr6":0,"D1":0,"D2":0, "gpus":[{"hash":28.746, "temp":"43", "fan":83},{"hash":28.975, "temp":"48", "fan":83},{"hash":29.979, "temp":"43", "fan":83},{"hash":28.076, "temp":"48", "fan":83}]}]}