{"MaxTotalHashRate":2605.9870,"CurrentTotalHashRate":2444.165,"LastUpdateDate":"Apr 17 2018  1:26AM","RIGs":7,"GPUs":85,"Miners":[{ "miner":"Row1", "MinerID":1024, "cards":13,"IPAddress":"10.0.1.137", "maxhash":389.6360, "hash":356.886,"Min30":0,"Hr2":0,"Hr6":1,"D1":0,"D2":4, "gpus":[{"hash":29.721, "temp":"54", "fan":83},{"hash":29.722, "temp":"69", "fan":83},{"hash":29.721, "temp":"50", "fan":83},{"hash":29.721, "temp":"66", "fan":83},{"hash":29.731, "temp":"57", "fan":83},{"hash":29.725, "temp":"65", "fan":83},{"hash":29.963, "temp":"63", "fan":83},{"hash":29.710, "temp":"67", "fan":83},{"hash":29.726, "temp":"58", "fan":83},{"hash":29.723, "temp":"59", "fan":83},{"hash":0.000, "temp":"36", "fan":83},{"hash":29.710, "temp":"62", "fan":83},{"hash":29.708, "temp":"63", "fan":83}]},{ "miner":"Row2", "MinerID":1025, "cards":12,"IPAddress":"10.0.1.138", "maxhash":359.8320, "hash":273.632,"Min30":1,"Hr2":2,"Hr6":6,"D1":2,"D2":13, "gpus":[{"hash":28.935, "temp":"65", "fan":100},{"hash":24.459, "temp":"63", "fan":100},{"hash":28.996, "temp":"74", "fan":100},{"hash":28.983, "temp":"66", "fan":100},{"hash":28.967, "temp":"77", "fan":100},{"hash":28.967, "temp":"62", "fan":100},{"hash":29.255, "temp":"43", "fan":100},{"hash":28.042, "temp":"47", "fan":100},{"hash":17.055, "temp":"54", "fan":100},{"hash":29.968, "temp":"43", "fan":100},{"hash":0.000, "temp":"42", "fan":100},{"hash":0.000, "temp":"35", "fan":100}]},{ "miner":"Row3", "MinerID":1026, "cards":13,"IPAddress":"10.0.1.76", "maxhash":404.9110, "hash":403.977,"Min30":0,"Hr2":0,"Hr6":0,"D1":0,"D2":1, "gpus":[{"hash":30.454, "temp":"51", "fan":80},{"hash":31.053, "temp":"49", "fan":80},{"hash":31.143, "temp":"51", "fan":80},{"hash":31.132, "temp":"51", "fan":80},{"hash":31.144, "temp":"51", "fan":80},{"hash":31.143, "temp":"49", "fan":80},{"hash":31.121, "temp":"52", "fan":80},{"hash":31.111, "temp":"53", "fan":80},{"hash":31.145, "temp":"53", "fan":80},{"hash":31.134, "temp":"48", "fan":80},{"hash":31.141, "temp":"50", "fan":80},{"hash":31.117, "temp":"46", "fan":80},{"hash":31.133, "temp":"54", "fan":80}]},{ "miner":"Row4", "MinerID":1027, "cards":13,"IPAddress":"10.0.1.139", "maxhash":382.7720, "hash":382.375,"Min30":0,"Hr2":0,"Hr6":1,"D1":0,"D2":4, "gpus":[{"hash":29.359, "temp":"54", "fan":83},{"hash":29.414, "temp":"69", "fan":83},{"hash":29.423, "temp":"54", "fan":83},{"hash":29.412, "temp":"61", "fan":83},{"hash":29.440, "temp":"63", "fan":83},{"hash":29.406, "temp":"64", "fan":83},{"hash":29.335, "temp":"59", "fan":83},{"hash":29.419, "temp":"69", "fan":83},{"hash":29.431, "temp":"68", "fan":83},{"hash":29.432, "temp":"69", "fan":83},{"hash":29.430, "temp":"59", "fan":83},{"hash":29.431, "temp":"57", "fan":83},{"hash":29.438, "temp":"59", "fan":83}]},{ "miner":"Row5", "MinerID":1028, "cards":13,"IPAddress":"10.0.1.62", "maxhash":407.6540, "hash":375.061,"Min30":0,"Hr2":0,"Hr6":1,"D1":0,"D2":4, "gpus":[{"hash":31.151, "temp":"54", "fan":80},{"hash":12.423, "temp":"43", "fan":80},{"hash":31.168, "temp":"56", "fan":80},{"hash":25.319, "temp":"58", "fan":80},{"hash":31.347, "temp":"62", "fan":80},{"hash":25.342, "temp":"64", "fan":80},{"hash":31.157, "temp":"43", "fan":80},{"hash":31.348, "temp":"62", "fan":80},{"hash":31.173, "temp":"66", "fan":80},{"hash":31.152, "temp":"52", "fan":80},{"hash":31.166, "temp":"56", "fan":80},{"hash":31.151, "temp":"58", "fan":80},{"hash":31.156, "temp":"60", "fan":80}]},{ "miner":"Row6", "MinerID":1029, "cards":12,"IPAddress":"10.0.1.140", "maxhash":381.4440, "hash":377.989,"Min30":0,"Hr2":0,"Hr6":0,"D1":0,"D2":1, "gpus":[{"hash":31.134, "temp":"59", "fan":83},{"hash":31.120, "temp":"55", "fan":83},{"hash":31.778, "temp":"59", "fan":83},{"hash":31.753, "temp":"64", "fan":83},{"hash":31.780, "temp":"63", "fan":83},{"hash":31.746, "temp":"44", "fan":83},{"hash":31.789, "temp":"65", "fan":83},{"hash":31.756, "temp":"67", "fan":83},{"hash":31.127, "temp":"61", "fan":83},{"hash":31.129, "temp":"59", "fan":83},{"hash":31.126, "temp":"60", "fan":83},{"hash":31.744, "temp":"60", "fan":83}]},{ "miner":"Row7", "MinerID":1030, "cards":9,"IPAddress":"10.0.1.88", "maxhash":279.7380, "hash":274.245,"Min30":0,"Hr2":0,"Hr6":0,"D1":0,"D2":1, "gpus":[{"hash":30.269, "temp":"66", "fan":83},{"hash":30.320, "temp":"62", "fan":83},{"hash":31.078, "temp":"50", "fan":83},{"hash":30.825, "temp":"52", "fan":83},{"hash":30.322, "temp":"69", "fan":83},{"hash":30.325, "temp":"65", "fan":83},{"hash":30.311, "temp":"64", "fan":83},{"hash":30.288, "temp":"63", "fan":83},{"hash":30.503, "temp":"51", "fan":83}]}]}