{"MaxTotalHashRate":2610.5070,"CurrentTotalHashRate":2196.039,"LastUpdateDate":"Apr 18 2018 12:05PM","RIGs":7,"GPUs":85,"Miners":[{ "miner":"Row1", "MinerID":1024, "cards":13,"IPAddress":"10.0.1.137", "maxhash":391.1700, "hash":0.000,"Min30":1,"Hr2":1,"Hr6":2,"D1":2,"D2":14, "gpus":[{"hash":0.000, "temp":"31", "fan":83},{"hash":0.000, "temp":"46", "fan":83},{"hash":0.000, "temp":"30", "fan":83},{"hash":0.000, "temp":"35", "fan":83},{"hash":0.000, "temp":"32", "fan":83},{"hash":0.000, "temp":"38", "fan":83},{"hash":0.000, "temp":"37", "fan":83},{"hash":0.000, "temp":"36", "fan":83},{"hash":0.000, "temp":"35", "fan":83},{"hash":0.000, "temp":"34", "fan":83},{"hash":0.000, "temp":"29", "fan":83},{"hash":0.000, "temp":"36", "fan":83},{"hash":0.000, "temp":"38", "fan":83}]},{ "miner":"Row2", "MinerID":1025, "cards":12,"IPAddress":"10.0.1.138", "maxhash":363.0240, "hash":351.874,"Min30":1,"Hr2":1,"Hr6":1,"D1":1,"D2":10, "gpus":[{"hash":30.023, "temp":"54", "fan":83},{"hash":25.631, "temp":"54", "fan":83},{"hash":30.037, "temp":"62", "fan":83},{"hash":30.069, "temp":"61", "fan":83},{"hash":28.978, "temp":"63", "fan":83},{"hash":30.076, "temp":"55", "fan":83},{"hash":29.979, "temp":"40", "fan":83},{"hash":29.107, "temp":"42", "fan":83},{"hash":29.240, "temp":"56", "fan":83},{"hash":30.252, "temp":"42", "fan":83},{"hash":29.245, "temp":"53", "fan":83},{"hash":29.232, "temp":"46", "fan":83}]},{ "miner":"Row3", "MinerID":1026, "cards":13,"IPAddress":"10.0.1.76", "maxhash":405.1320, "hash":404.551,"Min30":0,"Hr2":0,"Hr6":0,"D1":0,"D2":3, "gpus":[{"hash":31.150, "temp":"53", "fan":80},{"hash":31.070, "temp":"54", "fan":80},{"hash":31.123, "temp":"56", "fan":80},{"hash":31.133, "temp":"57", "fan":80},{"hash":31.130, "temp":"58", "fan":80},{"hash":31.121, "temp":"58", "fan":80},{"hash":31.088, "temp":"51", "fan":80},{"hash":31.138, "temp":"63", "fan":80},{"hash":31.125, "temp":"61", "fan":80},{"hash":31.119, "temp":"55", "fan":80},{"hash":31.124, "temp":"49", "fan":80},{"hash":31.139, "temp":"46", "fan":80},{"hash":31.086, "temp":"61", "fan":80}]},{ "miner":"Row4", "MinerID":1027, "cards":13,"IPAddress":"10.0.1.139", "maxhash":382.8370, "hash":382.521,"Min30":0,"Hr2":0,"Hr6":0,"D1":0,"D2":1, "gpus":[{"hash":29.394, "temp":"56", "fan":83},{"hash":29.431, "temp":"69", "fan":83},{"hash":29.433, "temp":"55", "fan":83},{"hash":29.442, "temp":"63", "fan":83},{"hash":29.422, "temp":"65", "fan":83},{"hash":29.432, "temp":"60", "fan":83},{"hash":29.447, "temp":"58", "fan":83},{"hash":29.445, "temp":"68", "fan":83},{"hash":29.445, "temp":"65", "fan":83},{"hash":29.438, "temp":"69", "fan":83},{"hash":29.390, "temp":"60", "fan":83},{"hash":29.433, "temp":"59", "fan":83},{"hash":29.363, "temp":"61", "fan":83}]},{ "miner":"Row5", "MinerID":1028, "cards":13,"IPAddress":"10.0.1.62", "maxhash":407.3810, "hash":404.813,"Min30":0,"Hr2":0,"Hr6":0,"D1":0,"D2":4, "gpus":[{"hash":31.124, "temp":"56", "fan":80},{"hash":31.132, "temp":"54", "fan":80},{"hash":31.126, "temp":"57", "fan":80},{"hash":31.127, "temp":"52", "fan":80},{"hash":31.334, "temp":"57", "fan":80},{"hash":31.148, "temp":"60", "fan":80},{"hash":31.140, "temp":"46", "fan":80},{"hash":31.317, "temp":"54", "fan":80},{"hash":31.155, "temp":"50", "fan":80},{"hash":31.135, "temp":"51", "fan":80},{"hash":31.133, "temp":"57", "fan":80},{"hash":30.790, "temp":"57", "fan":80},{"hash":31.147, "temp":"58", "fan":80}]},{ "miner":"Row6", "MinerID":1029, "cards":12,"IPAddress":"10.0.1.140", "maxhash":381.3960, "hash":377.987,"Min30":0,"Hr2":1,"Hr6":1,"D1":1,"D2":3, "gpus":[{"hash":31.123, "temp":"57", "fan":83},{"hash":31.124, "temp":"52", "fan":83},{"hash":31.772, "temp":"63", "fan":83},{"hash":31.762, "temp":"66", "fan":83},{"hash":31.776, "temp":"65", "fan":83},{"hash":31.739, "temp":"43", "fan":83},{"hash":31.740, "temp":"66", "fan":83},{"hash":31.765, "temp":"69", "fan":83},{"hash":31.142, "temp":"60", "fan":83},{"hash":31.134, "temp":"60", "fan":83},{"hash":31.132, "temp":"64", "fan":83},{"hash":31.771, "temp":"61", "fan":83}]},{ "miner":"Row7", "MinerID":1030, "cards":9,"IPAddress":"10.0.1.65", "maxhash":279.5670, "hash":274.293,"Min30":1,"Hr2":1,"Hr6":5,"D1":12,"D2":21, "gpus":[{"hash":30.280, "temp":"64", "fan":83},{"hash":30.322, "temp":"61", "fan":83},{"hash":31.081, "temp":"49", "fan":83},{"hash":30.767, "temp":"49", "fan":83},{"hash":30.333, "temp":"66", "fan":83},{"hash":30.327, "temp":"61", "fan":83},{"hash":30.330, "temp":"63", "fan":83},{"hash":30.333, "temp":"69", "fan":83},{"hash":30.516, "temp":"51", "fan":83}]}]}