{"MaxTotalHashRate":1982.0610,"CurrentTotalHashRate":1951.118,"LastUpdateDate":"Mar  1 2018  3:28AM","RIGs":9,"GPUs":65,"Miners":[{ "miner":"Miner1", "MinerID":1012, "cards":7,"IPAddress":"10.0.1.61", "maxhash":210.6230, "hash":203.463,"Min30":0,"Hr2":0,"Hr6":0,"D1":0,"D2":0, "gpus":[{"hash":28.727, "temp":"60", "fan":83},{"hash":28.728, "temp":"56", "fan":83},{"hash":28.726, "temp":"58", "fan":83},{"hash":29.054, "temp":"61", "fan":83},{"hash":29.368, "temp":"49", "fan":83},{"hash":30.129, "temp":"44", "fan":83},{"hash":28.729, "temp":"55", "fan":83}]},{ "miner":"Miner11", "MinerID":1020, "cards":7,"IPAddress":"10.0.1.37", "maxhash":209.9300, "hash":207.282,"Min30":0,"Hr2":0,"Hr6":0,"D1":0,"D2":0, "gpus":[{"hash":29.379, "temp":"56", "fan":83},{"hash":29.383, "temp":"50", "fan":83},{"hash":29.961, "temp":"48", "fan":83},{"hash":29.946, "temp":"52", "fan":83},{"hash":29.986, "temp":"49", "fan":83},{"hash":29.962, "temp":"68", "fan":83},{"hash":28.662, "temp":"50", "fan":83}]},{ "miner":"Miner12", "MinerID":1016, "cards":8,"IPAddress":"10.0.1.63", "maxhash":242.0480, "hash":240.408,"Min30":0,"Hr2":0,"Hr6":1,"D1":1,"D2":4, "gpus":[{"hash":29.998, "temp":"61", "fan":83},{"hash":29.975, "temp":"67", "fan":83},{"hash":29.977, "temp":"59", "fan":83},{"hash":30.020, "temp":"53", "fan":83},{"hash":30.241, "temp":"55", "fan":83},{"hash":29.963, "temp":"58", "fan":83},{"hash":29.987, "temp":"57", "fan":83},{"hash":30.243, "temp":"61", "fan":83}]},{ "miner":"Miner13", "MinerID":1021, "cards":8,"IPAddress":"10.0.1.5", "maxhash":240.4480, "hash":240.492,"Min30":0,"Hr2":0,"Hr6":0,"D1":0,"D2":0, "gpus":[{"hash":29.917, "temp":"61", "fan":83},{"hash":30.037, "temp":"59", "fan":83},{"hash":30.043, "temp":"59", "fan":83},{"hash":30.325, "temp":"56", "fan":83},{"hash":30.053, "temp":"55", "fan":83},{"hash":30.031, "temp":"58", "fan":83},{"hash":30.037, "temp":"56", "fan":83},{"hash":30.045, "temp":"61", "fan":83}]},{ "miner":"Miner14", "MinerID":1014, "cards":7,"IPAddress":"10.0.1.88", "maxhash":219.2400, "hash":210.587,"Min30":0,"Hr2":0,"Hr6":0,"D1":0,"D2":0, "gpus":[{"hash":31.309, "temp":"47", "fan":83},{"hash":28.998, "temp":"44", "fan":83},{"hash":29.990, "temp":"58", "fan":83},{"hash":29.976, "temp":"59", "fan":83},{"hash":29.001, "temp":"60", "fan":83},{"hash":31.302, "temp":"47", "fan":83},{"hash":30.007, "temp":"68", "fan":83}]},{ "miner":"Miner21", "MinerID":1017, "cards":8,"IPAddress":"10.0.1.50", "maxhash":240.2800, "hash":238.947,"Min30":0,"Hr2":0,"Hr6":0,"D1":0,"D2":0, "gpus":[{"hash":29.611, "temp":"67", "fan":83},{"hash":29.408, "temp":"59", "fan":83},{"hash":30.027, "temp":"54", "fan":83},{"hash":30.021, "temp":"59", "fan":83},{"hash":30.037, "temp":"65", "fan":83},{"hash":30.041, "temp":"71", "fan":83},{"hash":29.759, "temp":"71", "fan":83},{"hash":30.039, "temp":"65", "fan":83}]},{ "miner":"Miner22", "MinerID":1018, "cards":8,"IPAddress":"10.0.1.65", "maxhash":249.2480, "hash":248.465,"Min30":0,"Hr2":0,"Hr6":0,"D1":0,"D2":0, "gpus":[{"hash":31.138, "temp":"53", "fan":80},{"hash":30.906, "temp":"50", "fan":80},{"hash":31.127, "temp":"53", "fan":80},{"hash":30.952, "temp":"43", "fan":80},{"hash":31.123, "temp":"51", "fan":80},{"hash":31.131, "temp":"56", "fan":80},{"hash":31.127, "temp":"52", "fan":80},{"hash":30.959, "temp":"47", "fan":80}]},{ "miner":"Miner23", "MinerID":1022, "cards":8,"IPAddress":"10.0.1.113", "maxhash":250.5120, "hash":247.525,"Min30":0,"Hr2":0,"Hr6":0,"D1":0,"D2":0, "gpus":[{"hash":31.193, "temp":"51", "fan":80},{"hash":28.946, "temp":"62", "fan":80},{"hash":31.255, "temp":"51", "fan":80},{"hash":31.228, "temp":"53", "fan":80},{"hash":31.225, "temp":"55", "fan":80},{"hash":31.248, "temp":"54", "fan":80},{"hash":31.206, "temp":"52", "fan":80},{"hash":31.221, "temp":"54", "fan":80}]},{ "miner":"Miner24", "MinerID":1023, "cards":4,"IPAddress":"10.0.1.70", "maxhash":119.7320, "hash":113.949,"Min30":0,"Hr2":0,"Hr6":0,"D1":0,"D2":0, "gpus":[{"hash":27.800, "temp":"44", "fan":83},{"hash":29.053, "temp":"49", "fan":83},{"hash":29.983, "temp":"44", "fan":83},{"hash":27.112, "temp":"50", "fan":83}]}]}