{"MaxTotalHashRate":1981.7390,"CurrentTotalHashRate":1957.014,"LastUpdateDate":"Feb 21 2018  5:17PM","RIGs":9,"GPUs":65,"Miners":[{ "miner":"Miner1", "MinerID":1012, "cards":7,"IPAddress":"10.0.1.61", "maxhash":212.4150, "hash":207.466,"Min30":0,"Hr2":0,"Hr6":0,"D1":3,"D2":11, "gpus":[{"hash":29.419, "temp":"64", "fan":83},{"hash":29.432, "temp":"61", "fan":83},{"hash":29.424, "temp":"64", "fan":83},{"hash":30.304, "temp":"60", "fan":83},{"hash":29.368, "temp":"50", "fan":83},{"hash":30.096, "temp":"46", "fan":83},{"hash":29.421, "temp":"59", "fan":83}]},{ "miner":"Miner11", "MinerID":1020, "cards":7,"IPAddress":"10.0.1.37", "maxhash":209.7760, "hash":207.166,"Min30":0,"Hr2":0,"Hr6":0,"D1":0,"D2":1, "gpus":[{"hash":29.397, "temp":"53", "fan":83},{"hash":29.345, "temp":"46", "fan":83},{"hash":30.013, "temp":"44", "fan":83},{"hash":29.999, "temp":"50", "fan":83},{"hash":29.972, "temp":"46", "fan":83},{"hash":29.953, "temp":"65", "fan":83},{"hash":28.484, "temp":"46", "fan":83}]},{ "miner":"Miner12", "MinerID":1016, "cards":8,"IPAddress":"10.0.1.63", "maxhash":241.9120, "hash":240.501,"Min30":0,"Hr2":0,"Hr6":0,"D1":1,"D2":2, "gpus":[{"hash":30.009, "temp":"58", "fan":83},{"hash":29.988, "temp":"65", "fan":83},{"hash":29.999, "temp":"57", "fan":83},{"hash":29.997, "temp":"50", "fan":83},{"hash":30.256, "temp":"52", "fan":83},{"hash":29.985, "temp":"56", "fan":83},{"hash":29.989, "temp":"55", "fan":83},{"hash":30.275, "temp":"60", "fan":83}]},{ "miner":"Miner13", "MinerID":1021, "cards":8,"IPAddress":"10.0.1.5", "maxhash":242.4160, "hash":240.042,"Min30":0,"Hr2":0,"Hr6":0,"D1":0,"D2":2, "gpus":[{"hash":29.932, "temp":"60", "fan":83},{"hash":29.990, "temp":"57", "fan":83},{"hash":29.965, "temp":"57", "fan":83},{"hash":30.239, "temp":"54", "fan":83},{"hash":29.968, "temp":"53", "fan":83},{"hash":30.001, "temp":"56", "fan":83},{"hash":29.971, "temp":"53", "fan":83},{"hash":29.973, "temp":"59", "fan":83}]},{ "miner":"Miner14", "MinerID":1014, "cards":7,"IPAddress":"10.0.1.88", "maxhash":219.4640, "hash":210.589,"Min30":0,"Hr2":0,"Hr6":0,"D1":0,"D2":1, "gpus":[{"hash":31.326, "temp":"45", "fan":83},{"hash":28.977, "temp":"42", "fan":83},{"hash":29.975, "temp":"56", "fan":83},{"hash":29.977, "temp":"57", "fan":83},{"hash":28.991, "temp":"58", "fan":83},{"hash":31.329, "temp":"45", "fan":83},{"hash":30.010, "temp":"67", "fan":83}]},{ "miner":"Miner21", "MinerID":1017, "cards":8,"IPAddress":"10.0.1.50", "maxhash":239.9440, "hash":239.335,"Min30":0,"Hr2":0,"Hr6":0,"D1":2,"D2":4, "gpus":[{"hash":29.963, "temp":"64", "fan":83},{"hash":29.839, "temp":"56", "fan":83},{"hash":29.972, "temp":"52", "fan":83},{"hash":29.940, "temp":"57", "fan":83},{"hash":29.965, "temp":"62", "fan":83},{"hash":29.982, "temp":"67", "fan":83},{"hash":29.694, "temp":"68", "fan":83},{"hash":29.977, "temp":"62", "fan":83}]},{ "miner":"Miner22", "MinerID":1018, "cards":8,"IPAddress":"10.0.1.65", "maxhash":249.4720, "hash":248.326,"Min30":0,"Hr2":0,"Hr6":0,"D1":1,"D2":3, "gpus":[{"hash":31.142, "temp":"50", "fan":80},{"hash":30.904, "temp":"48", "fan":80},{"hash":31.103, "temp":"51", "fan":80},{"hash":30.906, "temp":"42", "fan":80},{"hash":31.091, "temp":"48", "fan":80},{"hash":31.147, "temp":"53", "fan":80},{"hash":31.128, "temp":"50", "fan":80},{"hash":30.902, "temp":"46", "fan":80}]},{ "miner":"Miner23", "MinerID":1022, "cards":8,"IPAddress":"10.0.1.113", "maxhash":250.3200, "hash":247.791,"Min30":0,"Hr2":0,"Hr6":0,"D1":0,"D2":0, "gpus":[{"hash":31.269, "temp":"48", "fan":80},{"hash":28.972, "temp":"65", "fan":80},{"hash":31.275, "temp":"49", "fan":80},{"hash":31.246, "temp":"51", "fan":80},{"hash":31.253, "temp":"53", "fan":80},{"hash":31.242, "temp":"52", "fan":80},{"hash":31.268, "temp":"50", "fan":80},{"hash":31.263, "temp":"52", "fan":80}]},{ "miner":"Miner24", "MinerID":1023, "cards":4,"IPAddress":"10.0.1.70", "maxhash":116.0200, "hash":115.798,"Min30":0,"Hr2":0,"Hr6":0,"D1":0,"D2":0, "gpus":[{"hash":28.884, "temp":"43", "fan":83},{"hash":28.980, "temp":"48", "fan":83},{"hash":29.001, "temp":"43", "fan":83},{"hash":28.932, "temp":"49", "fan":83}]}]}