{"MaxTotalHashRate":2637.7750,"CurrentTotalHashRate":2261.121,"LastUpdateDate":"Jun  9 2018 10:46PM","RIGs":7,"GPUs":86,"Miners":[{ "miner":"Miner02", "MinerID":1025, "cards":13,"IPAddress":"10.0.1.138", "maxhash":391.1050, "hash":383.568,"Min30":0,"Hr2":0,"Hr6":0,"D1":1,"D2":2, "gpus":[{"hash":30.066, "temp":"64", "fan":83},{"hash":29.158, "temp":"58", "fan":83},{"hash":30.083, "temp":"67", "fan":83},{"hash":30.080, "temp":"62", "fan":83},{"hash":29.714, "temp":"63", "fan":83},{"hash":30.075, "temp":"56", "fan":83},{"hash":29.984, "temp":"46", "fan":83},{"hash":29.254, "temp":"56", "fan":83},{"hash":28.039, "temp":"44", "fan":83},{"hash":29.379, "temp":"57", "fan":83},{"hash":29.241, "temp":"50", "fan":83},{"hash":29.237, "temp":"56", "fan":83},{"hash":29.252, "temp":"45", "fan":83}]},{ "miner":"Miner03", "MinerID":1026, "cards":13,"IPAddress":"10.0.1.76", "maxhash":404.9890, "hash":404.657,"Min30":0,"Hr2":0,"Hr6":0,"D1":1,"D2":1, "gpus":[{"hash":31.125, "temp":"59", "fan":80},{"hash":31.053, "temp":"59", "fan":80},{"hash":31.145, "temp":"56", "fan":80},{"hash":31.134, "temp":"59", "fan":80},{"hash":31.116, "temp":"60", "fan":80},{"hash":31.147, "temp":"59", "fan":80},{"hash":31.143, "temp":"57", "fan":80},{"hash":31.145, "temp":"54", "fan":80},{"hash":31.120, "temp":"51", "fan":80},{"hash":31.145, "temp":"57", "fan":80},{"hash":31.137, "temp":"55", "fan":80},{"hash":31.112, "temp":"51", "fan":80},{"hash":31.127, "temp":"57", "fan":80}]},{ "miner":"Miner04", "MinerID":1027, "cards":13,"IPAddress":"10.0.1.139", "maxhash":394.3160, "hash":390.914,"Min30":0,"Hr2":0,"Hr6":0,"D1":1,"D2":4, "gpus":[{"hash":29.987, "temp":"59", "fan":83},{"hash":30.308, "temp":"73", "fan":83},{"hash":30.323, "temp":"59", "fan":83},{"hash":29.990, "temp":"62", "fan":83},{"hash":29.810, "temp":"63", "fan":83},{"hash":30.317, "temp":"59", "fan":83},{"hash":29.252, "temp":"64", "fan":83},{"hash":29.987, "temp":"65", "fan":83},{"hash":29.977, "temp":"62", "fan":83},{"hash":29.990, "temp":"70", "fan":83},{"hash":30.326, "temp":"63", "fan":83},{"hash":30.320, "temp":"59", "fan":83},{"hash":30.320, "temp":"60", "fan":83}]},{ "miner":"Miner05", "MinerID":1028, "cards":13,"IPAddress":"10.0.1.62", "maxhash":405.0150, "hash":403.633,"Min30":0,"Hr2":0,"Hr6":0,"D1":2,"D2":3, "gpus":[{"hash":31.130, "temp":"52", "fan":80},{"hash":31.122, "temp":"57", "fan":80},{"hash":31.126, "temp":"63", "fan":80},{"hash":31.143, "temp":"59", "fan":80},{"hash":31.049, "temp":"55", "fan":80},{"hash":30.819, "temp":"60", "fan":80},{"hash":31.115, "temp":"50", "fan":80},{"hash":31.156, "temp":"56", "fan":80},{"hash":31.136, "temp":"56", "fan":80},{"hash":31.117, "temp":"55", "fan":80},{"hash":30.455, "temp":"57", "fan":80},{"hash":31.130, "temp":"59", "fan":80},{"hash":31.130, "temp":"61", "fan":80}]},{ "miner":"Miner06", "MinerID":1029, "cards":12,"IPAddress":"10.0.1.140", "maxhash":380.6520, "hash":375.709,"Min30":0,"Hr2":0,"Hr6":0,"D1":1,"D2":1, "gpus":[{"hash":31.160, "temp":"61", "fan":83},{"hash":31.132, "temp":"57", "fan":83},{"hash":31.136, "temp":"62", "fan":83},{"hash":31.145, "temp":"65", "fan":83},{"hash":31.156, "temp":"62", "fan":83},{"hash":31.475, "temp":"52", "fan":83},{"hash":31.739, "temp":"51", "fan":83},{"hash":30.820, "temp":"50", "fan":83},{"hash":31.497, "temp":"56", "fan":83},{"hash":31.478, "temp":"56", "fan":83},{"hash":31.480, "temp":"52", "fan":83},{"hash":31.485, "temp":"62", "fan":83}]},{ "miner":"Miner07", "MinerID":1030, "cards":10,"IPAddress":"10.0.1.65", "maxhash":307.1100, "hash":302.640,"Min30":0,"Hr2":0,"Hr6":0,"D1":2,"D2":2, "gpus":[{"hash":30.318, "temp":"66", "fan":83},{"hash":30.343, "temp":"61", "fan":83},{"hash":30.727, "temp":"50", "fan":83},{"hash":30.133, "temp":"55", "fan":83},{"hash":30.330, "temp":"65", "fan":83},{"hash":30.334, "temp":"61", "fan":83},{"hash":30.151, "temp":"66", "fan":83},{"hash":29.979, "temp":"64", "fan":83},{"hash":29.985, "temp":"67", "fan":83},{"hash":30.337, "temp":"52", "fan":83}]}]}