{"MaxTotalHashRate":1960.4390,"CurrentTotalHashRate":1923.465,"LastUpdateDate":"Feb 19 2018  3:33AM","Miners":[{ "miner":"Miner1", "MinerID":1012, "cards":7,"IPAddress":"10.0.1.61", "maxhash":215.7190, "hash":205.659,"Min30":0,"Hr2":0,"Hr6":1,"D1":0,"D2":2, "gpus":[{"hash":29.068, "temp":61, "fan":83},{"hash":29.024, "temp":57, "fan":83},{"hash":29.056, "temp":58, "fan":83},{"hash":29.077, "temp":57, "fan":83},{"hash":30.108, "temp":49, "fan":83},{"hash":30.796, "temp":44, "fan":83},{"hash":28.526, "temp":55, "fan":83}]},{ "miner":"Miner11", "MinerID":1020, "cards":7,"IPAddress":"10.0.1.37", "maxhash":203.2170, "hash":193.975,"Min30":0,"Hr2":0,"Hr6":1,"D1":0,"D2":2, "gpus":[{"hash":28.256, "temp":53, "fan":83},{"hash":28.995, "temp":51, "fan":83},{"hash":28.989, "temp":52, "fan":83},{"hash":28.984, "temp":49, "fan":83},{"hash":28.995, "temp":48, "fan":83},{"hash":28.978, "temp":64, "fan":83},{"hash":20.774, "temp":48, "fan":83}]},{ "miner":"Miner12", "MinerID":1016, "cards":8,"IPAddress":"10.0.1.63", "maxhash":242.2080, "hash":240.385,"Min30":0,"Hr2":0,"Hr6":1,"D1":1,"D2":8, "gpus":[{"hash":29.966, "temp":60, "fan":83},{"hash":29.976, "temp":67, "fan":83},{"hash":29.980, "temp":58, "fan":83},{"hash":29.972, "temp":52, "fan":83},{"hash":30.250, "temp":52, "fan":83},{"hash":30.003, "temp":59, "fan":83},{"hash":29.979, "temp":58, "fan":83},{"hash":30.255, "temp":61, "fan":83}]},{ "miner":"Miner13", "MinerID":1021, "cards":8,"IPAddress":"10.0.1.5", "maxhash":231.9120, "hash":231.867,"Min30":0,"Hr2":0,"Hr6":0,"D1":0,"D2":0, "gpus":[{"hash":28.975, "temp":59, "fan":83},{"hash":29.004, "temp":59, "fan":83},{"hash":29.008, "temp":59, "fan":83},{"hash":28.970, "temp":56, "fan":83},{"hash":28.974, "temp":51, "fan":83},{"hash":28.994, "temp":57, "fan":83},{"hash":28.967, "temp":53, "fan":83},{"hash":28.971, "temp":61, "fan":83}]},{ "miner":"Miner14", "MinerID":1014, "cards":7,"IPAddress":"10.0.1.88", "maxhash":219.3870, "hash":207.606,"Min30":0,"Hr2":0,"Hr6":0,"D1":0,"D2":0, "gpus":[{"hash":31.317, "temp":42, "fan":83},{"hash":28.987, "temp":41, "fan":83},{"hash":28.983, "temp":57, "fan":83},{"hash":28.992, "temp":54, "fan":83},{"hash":28.977, "temp":64, "fan":83},{"hash":31.340, "temp":45, "fan":83},{"hash":29.007, "temp":69, "fan":83}]},{ "miner":"Miner21", "MinerID":1017, "cards":8,"IPAddress":"10.0.1.50", "maxhash":232.1200, "hash":231.828,"Min30":0,"Hr2":0,"Hr6":0,"D1":0,"D2":0, "gpus":[{"hash":28.962, "temp":61, "fan":83},{"hash":28.831, "temp":57, "fan":83},{"hash":29.003, "temp":52, "fan":83},{"hash":29.011, "temp":57, "fan":83},{"hash":28.991, "temp":61, "fan":83},{"hash":29.016, "temp":66, "fan":83},{"hash":28.999, "temp":64, "fan":83},{"hash":29.011, "temp":62, "fan":83}]},{ "miner":"Miner22", "MinerID":1018, "cards":8,"IPAddress":"10.0.1.65", "maxhash":249.2640, "hash":248.428,"Min30":0,"Hr2":0,"Hr6":0,"D1":0,"D2":0, "gpus":[{"hash":31.146, "temp":55, "fan":80},{"hash":30.911, "temp":43, "fan":80},{"hash":31.128, "temp":51, "fan":80},{"hash":30.920, "temp":40, "fan":80},{"hash":31.127, "temp":54, "fan":80},{"hash":31.149, "temp":49, "fan":80},{"hash":31.137, "temp":55, "fan":80},{"hash":30.907, "temp":43, "fan":80}]},{ "miner":"Miner23", "MinerID":1022, "cards":8,"IPAddress":"10.0.1.113", "maxhash":250.5600, "hash":247.817,"Min30":0,"Hr2":0,"Hr6":0,"D1":0,"D2":0, "gpus":[{"hash":31.258, "temp":47, "fan":80},{"hash":28.975, "temp":58, "fan":80},{"hash":31.275, "temp":49, "fan":80},{"hash":31.276, "temp":50, "fan":80},{"hash":31.259, "temp":51, "fan":80},{"hash":31.262, "temp":49, "fan":80},{"hash":31.256, "temp":47, "fan":80},{"hash":31.253, "temp":51, "fan":80}]},{ "miner":"Miner24", "MinerID":1023, "cards":4,"IPAddress":"10.0.1.70", "maxhash":116.0520, "hash":115.900,"Min30":0,"Hr2":0,"Hr6":0,"D1":0,"D2":2, "gpus":[{"hash":28.887, "temp":43, "fan":83},{"hash":29.026, "temp":47, "fan":83},{"hash":29.044, "temp":42, "fan":83},{"hash":28.942, "temp":47, "fan":83}]}]}