{"MaxTotalHashRate":1961.0950,"CurrentTotalHashRate":1906.693,"LastUpdateDate":"Feb 18 2018 10:46AM","Miners":[{ "miner":"Miner1", "MinerID":1012, "cards":8,"IPAddress":"10.0.1.61", "maxhash":246.4320, "hash":234.789,"Min30":0,"Hr2":0,"Hr6":0,"D1":0,"D2":0, "gpus":[{"hash":29.147, "temp":52, "fan":83},{"hash":29.062, "temp":57, "fan":83},{"hash":29.060, "temp":62, "fan":83},{"hash":29.036, "temp":58, "fan":83},{"hash":29.084, "temp":56, "fan":83},{"hash":30.139, "temp":49, "fan":83},{"hash":30.801, "temp":46, "fan":83},{"hash":28.457, "temp":55, "fan":83}]},{ "miner":"Miner11", "MinerID":1020, "cards":8,"IPAddress":"10.0.1.37", "maxhash":231.9680, "hash":224.510,"Min30":0,"Hr2":0,"Hr6":0,"D1":0,"D2":1, "gpus":[{"hash":28.114, "temp":53, "fan":83},{"hash":29.003, "temp":48, "fan":83},{"hash":22.452, "temp":46, "fan":83},{"hash":28.997, "temp":53, "fan":83},{"hash":28.974, "temp":63, "fan":83},{"hash":28.979, "temp":38, "fan":83},{"hash":28.996, "temp":45, "fan":83},{"hash":28.991, "temp":49, "fan":83}]},{ "miner":"Miner12", "MinerID":1016, "cards":8,"IPAddress":"10.0.1.63", "maxhash":242.0000, "hash":230.283,"Min30":0,"Hr2":1,"Hr6":3,"D1":4,"D2":7, "gpus":[{"hash":29.981, "temp":59, "fan":83},{"hash":29.977, "temp":66, "fan":83},{"hash":29.988, "temp":57, "fan":83},{"hash":29.993, "temp":51, "fan":83},{"hash":30.243, "temp":51, "fan":83},{"hash":29.981, "temp":58, "fan":83},{"hash":29.982, "temp":56, "fan":83},{"hash":20.134, "temp":59, "fan":83}]},{ "miner":"Miner13", "MinerID":1021, "cards":8,"IPAddress":"10.0.1.5", "maxhash":231.9760, "hash":223.235,"Min30":0,"Hr2":0,"Hr6":0,"D1":0,"D2":1, "gpus":[{"hash":29.006, "temp":59, "fan":83},{"hash":29.006, "temp":58, "fan":83},{"hash":29.022, "temp":58, "fan":83},{"hash":29.005, "temp":55, "fan":83},{"hash":20.159, "temp":50, "fan":83},{"hash":29.000, "temp":56, "fan":83},{"hash":29.025, "temp":53, "fan":83},{"hash":29.007, "temp":60, "fan":83}]},{ "miner":"Miner14", "MinerID":1014, "cards":7,"IPAddress":"10.0.1.88", "maxhash":219.3030, "hash":208.036,"Min30":0,"Hr2":0,"Hr6":0,"D1":0,"D2":0, "gpus":[{"hash":31.403, "temp":42, "fan":83},{"hash":29.063, "temp":40, "fan":83},{"hash":28.979, "temp":56, "fan":83},{"hash":29.065, "temp":53, "fan":83},{"hash":29.063, "temp":62, "fan":83},{"hash":31.403, "temp":44, "fan":83},{"hash":29.057, "temp":69, "fan":83}]},{ "miner":"Miner21", "MinerID":1017, "cards":8,"IPAddress":"10.0.1.50", "maxhash":232.0960, "hash":231.949,"Min30":0,"Hr2":0,"Hr6":0,"D1":0,"D2":0, "gpus":[{"hash":28.937, "temp":59, "fan":83},{"hash":28.951, "temp":54, "fan":83},{"hash":29.000, "temp":49, "fan":83},{"hash":28.996, "temp":56, "fan":83},{"hash":29.021, "temp":57, "fan":83},{"hash":29.028, "temp":63, "fan":83},{"hash":28.992, "temp":62, "fan":83},{"hash":29.021, "temp":60, "fan":83}]},{ "miner":"Miner22", "MinerID":1018, "cards":8,"IPAddress":"10.0.1.65", "maxhash":249.2000, "hash":248.324,"Min30":0,"Hr2":0,"Hr6":0,"D1":0,"D2":1, "gpus":[{"hash":31.104, "temp":53, "fan":80},{"hash":30.902, "temp":42, "fan":80},{"hash":31.104, "temp":50, "fan":80},{"hash":30.908, "temp":39, "fan":80},{"hash":31.128, "temp":52, "fan":80},{"hash":31.146, "temp":48, "fan":80},{"hash":31.121, "temp":53, "fan":80},{"hash":30.908, "temp":42, "fan":80}]},{ "miner":"Miner23", "MinerID":1022, "cards":8,"IPAddress":"10.0.1.113", "maxhash":250.2080, "hash":247.737,"Min30":0,"Hr2":0,"Hr6":0,"D1":0,"D2":1, "gpus":[{"hash":31.251, "temp":46, "fan":80},{"hash":28.976, "temp":56, "fan":80},{"hash":31.252, "temp":48, "fan":80},{"hash":31.253, "temp":49, "fan":80},{"hash":31.251, "temp":50, "fan":80},{"hash":31.253, "temp":49, "fan":80},{"hash":31.249, "temp":45, "fan":80},{"hash":31.248, "temp":50, "fan":80}]},{ "miner":"Miner24", "MinerID":1023, "cards":2,"IPAddress":"10.0.1.70", "maxhash":57.9120, "hash":57.830,"Min30":0,"Hr2":0,"Hr6":0,"D1":0,"D2":0, "gpus":[{"hash":28.914, "temp":40, "fan":83},{"hash":28.916, "temp":45, "fan":83}]}]}