{"MaxTotalHashRate":2199.5070,"CurrentTotalHashRate":1719.232,"LastUpdateDate":"Mar  7 2018 10:05AM","RIGs":10,"GPUs":72,"Miners":[{ "miner":"Miner11", "MinerID":1020, "cards":7,"IPAddress":"10.0.1.37", "maxhash":209.5730, "hash":207.033,"Min30":0,"Hr2":0,"Hr6":0,"D1":0,"D2":0, "gpus":[{"hash":29.332, "temp":"57", "fan":83},{"hash":29.325, "temp":"56", "fan":83},{"hash":29.920, "temp":"49", "fan":83},{"hash":29.926, "temp":"54", "fan":83},{"hash":29.918, "temp":"54", "fan":83},{"hash":29.955, "temp":"54", "fan":83},{"hash":28.655, "temp":"45", "fan":83}]},{ "miner":"Miner12", "MinerID":1016, "cards":8,"IPAddress":"10.0.1.63", "maxhash":242.3680, "hash":240.408,"Min30":0,"Hr2":0,"Hr6":1,"D1":1,"D2":4, "gpus":[{"hash":29.989, "temp":"58", "fan":83},{"hash":29.981, "temp":"63", "fan":83},{"hash":29.979, "temp":"54", "fan":83},{"hash":29.975, "temp":"51", "fan":83},{"hash":30.273, "temp":"53", "fan":83},{"hash":29.976, "temp":"56", "fan":83},{"hash":29.976, "temp":"55", "fan":83},{"hash":30.255, "temp":"57", "fan":83}]},{ "miner":"Miner13", "MinerID":1021, "cards":8,"IPAddress":"10.0.1.5", "maxhash":242.5520, "hash":240.581,"Min30":0,"Hr2":0,"Hr6":1,"D1":2,"D2":3, "gpus":[{"hash":29.985, "temp":"60", "fan":83},{"hash":30.038, "temp":"58", "fan":83},{"hash":30.041, "temp":"60", "fan":83},{"hash":30.321, "temp":"56", "fan":83},{"hash":30.049, "temp":"53", "fan":83},{"hash":30.051, "temp":"56", "fan":83},{"hash":30.055, "temp":"53", "fan":83},{"hash":30.040, "temp":"60", "fan":83}]},{ "miner":"Miner14", "MinerID":1014, "cards":7,"IPAddress":"10.0.1.88", "maxhash":219.1490, "hash":210.508,"Min30":0,"Hr2":0,"Hr6":1,"D1":2,"D2":4, "gpus":[{"hash":31.315, "temp":"42", "fan":83},{"hash":28.978, "temp":"39", "fan":83},{"hash":29.976, "temp":"54", "fan":83},{"hash":29.978, "temp":"56", "fan":83},{"hash":28.972, "temp":"59", "fan":83},{"hash":31.304, "temp":"43", "fan":83},{"hash":29.982, "temp":"68", "fan":83}]},{ "miner":"Miner21", "MinerID":1017, "cards":8,"IPAddress":"10.0.1.50", "maxhash":240.2640, "hash":209.824,"Min30":0,"Hr2":0,"Hr6":0,"D1":0,"D2":0, "gpus":[{"hash":0.000, "temp":"43", "fan":83},{"hash":29.944, "temp":"56", "fan":83},{"hash":30.024, "temp":"53", "fan":83},{"hash":29.994, "temp":"56", "fan":83},{"hash":30.030, "temp":"62", "fan":83},{"hash":30.033, "temp":"69", "fan":83},{"hash":29.758, "temp":"66", "fan":83},{"hash":30.037, "temp":"61", "fan":83}]},{ "miner":"Miner22", "MinerID":1018, "cards":8,"IPAddress":"10.0.1.65", "maxhash":249.7280, "hash":249.038,"Min30":0,"Hr2":0,"Hr6":0,"D1":0,"D2":0, "gpus":[{"hash":31.222, "temp":"47", "fan":80},{"hash":31.004, "temp":"43", "fan":80},{"hash":31.203, "temp":"48", "fan":80},{"hash":30.991, "temp":"42", "fan":80},{"hash":31.212, "temp":"47", "fan":80},{"hash":31.195, "temp":"48", "fan":80},{"hash":31.209, "temp":"49", "fan":80},{"hash":30.998, "temp":"45", "fan":80}]},{ "miner":"Miner23", "MinerID":1022, "cards":8,"IPAddress":"10.0.1.113", "maxhash":250.3840, "hash":247.500,"Min30":0,"Hr2":0,"Hr6":0,"D1":0,"D2":0, "gpus":[{"hash":31.227, "temp":"48", "fan":80},{"hash":28.944, "temp":"58", "fan":80},{"hash":31.226, "temp":"51", "fan":80},{"hash":31.177, "temp":"51", "fan":80},{"hash":31.179, "temp":"53", "fan":80},{"hash":31.248, "temp":"51", "fan":80},{"hash":31.270, "temp":"49", "fan":80},{"hash":31.226, "temp":"53", "fan":80}]},{ "miner":"Miner24", "MinerID":1023, "cards":4,"IPAddress":"10.0.1.70", "maxhash":119.8400, "hash":114.340,"Min30":0,"Hr2":0,"Hr6":0,"D1":0,"D2":0, "gpus":[{"hash":28.006, "temp":"43", "fan":83},{"hash":28.982, "temp":"47", "fan":83},{"hash":29.980, "temp":"42", "fan":83},{"hash":27.370, "temp":"48", "fan":83}]}]}