{"MaxTotalHashRate":2621.5830,"CurrentTotalHashRate":2464.759,"LastUpdateDate":"Apr 16 2018  7:37PM","RIGs":7,"GPUs":85,"Miners":[{ "miner":"Row1", "MinerID":1024, "cards":13,"IPAddress":"10.0.1.137", "maxhash":391.0400, "hash":360.665,"Min30":0,"Hr2":0,"Hr6":2,"D1":3,"D2":3, "gpus":[{"hash":30.047, "temp":"56", "fan":83},{"hash":30.070, "temp":"70", "fan":83},{"hash":30.058, "temp":"51", "fan":83},{"hash":30.073, "temp":"67", "fan":83},{"hash":30.065, "temp":"58", "fan":83},{"hash":30.073, "temp":"66", "fan":83},{"hash":29.962, "temp":"64", "fan":83},{"hash":30.072, "temp":"68", "fan":83},{"hash":30.067, "temp":"59", "fan":83},{"hash":30.038, "temp":"60", "fan":83},{"hash":0.000, "temp":"37", "fan":83},{"hash":30.067, "temp":"63", "fan":83},{"hash":30.067, "temp":"64", "fan":83}]},{ "miner":"Row2", "MinerID":1025, "cards":12,"IPAddress":"10.0.1.138", "maxhash":363.1680, "hash":281.171,"Min30":0,"Hr2":2,"Hr6":5,"D1":7,"D2":7, "gpus":[{"hash":29.995, "temp":"54", "fan":83},{"hash":25.619, "temp":"54", "fan":83},{"hash":30.064, "temp":"62", "fan":83},{"hash":30.066, "temp":"60", "fan":83},{"hash":0.000, "temp":"44", "fan":83},{"hash":30.067, "temp":"54", "fan":83},{"hash":30.148, "temp":"39", "fan":83},{"hash":29.141, "temp":"42", "fan":83},{"hash":22.166, "temp":"50", "fan":83},{"hash":30.239, "temp":"43", "fan":83},{"hash":23.661, "temp":"53", "fan":83},{"hash":0.000, "temp":"35", "fan":83}]},{ "miner":"Row3", "MinerID":1026, "cards":13,"IPAddress":"10.0.1.76", "maxhash":405.2360, "hash":403.991,"Min30":0,"Hr2":0,"Hr6":0,"D1":1,"D2":1, "gpus":[{"hash":30.532, "temp":"52", "fan":80},{"hash":31.047, "temp":"50", "fan":80},{"hash":31.141, "temp":"52", "fan":80},{"hash":31.122, "temp":"51", "fan":80},{"hash":31.132, "temp":"52", "fan":80},{"hash":31.130, "temp":"50", "fan":80},{"hash":31.108, "temp":"52", "fan":80},{"hash":31.101, "temp":"54", "fan":80},{"hash":31.145, "temp":"53", "fan":80},{"hash":31.132, "temp":"49", "fan":80},{"hash":31.143, "temp":"50", "fan":80},{"hash":31.130, "temp":"46", "fan":80},{"hash":31.121, "temp":"55", "fan":80}]},{ "miner":"Row4", "MinerID":1027, "cards":13,"IPAddress":"10.0.1.139", "maxhash":387.5300, "hash":357.486,"Min30":0,"Hr2":0,"Hr6":1,"D1":3,"D2":3, "gpus":[{"hash":29.729, "temp":"55", "fan":83},{"hash":29.798, "temp":"70", "fan":83},{"hash":29.785, "temp":"55", "fan":83},{"hash":29.795, "temp":"62", "fan":83},{"hash":29.803, "temp":"64", "fan":83},{"hash":29.806, "temp":"66", "fan":83},{"hash":0.000, "temp":"38", "fan":83},{"hash":29.792, "temp":"70", "fan":83},{"hash":29.769, "temp":"70", "fan":83},{"hash":29.789, "temp":"70", "fan":83},{"hash":29.814, "temp":"60", "fan":83},{"hash":29.805, "temp":"58", "fan":83},{"hash":29.795, "temp":"60", "fan":83}]},{ "miner":"Row5", "MinerID":1028, "cards":13,"IPAddress":"10.0.1.62", "maxhash":413.3220, "hash":409.264,"Min30":0,"Hr2":0,"Hr6":1,"D1":3,"D2":3, "gpus":[{"hash":31.800, "temp":"57", "fan":80},{"hash":31.758, "temp":"50", "fan":80},{"hash":31.781, "temp":"58", "fan":80},{"hash":31.795, "temp":"61", "fan":80},{"hash":31.328, "temp":"63", "fan":80},{"hash":30.980, "temp":"68", "fan":80},{"hash":31.127, "temp":"44", "fan":80},{"hash":31.143, "temp":"64", "fan":80},{"hash":31.754, "temp":"69", "fan":80},{"hash":31.778, "temp":"54", "fan":80},{"hash":30.477, "temp":"58", "fan":80},{"hash":31.755, "temp":"61", "fan":80},{"hash":31.782, "temp":"62", "fan":80}]},{ "miner":"Row6", "MinerID":1029, "cards":12,"IPAddress":"10.0.1.140", "maxhash":381.5400, "hash":377.892,"Min30":0,"Hr2":0,"Hr6":0,"D1":1,"D2":1, "gpus":[{"hash":31.108, "temp":"60", "fan":83},{"hash":31.116, "temp":"56", "fan":83},{"hash":31.776, "temp":"60", "fan":83},{"hash":31.748, "temp":"64", "fan":83},{"hash":31.758, "temp":"64", "fan":83},{"hash":31.722, "temp":"45", "fan":83},{"hash":31.772, "temp":"66", "fan":83},{"hash":31.760, "temp":"68", "fan":83},{"hash":31.124, "temp":"62", "fan":83},{"hash":31.131, "temp":"60", "fan":83},{"hash":31.110, "temp":"61", "fan":83},{"hash":31.761, "temp":"60", "fan":83}]},{ "miner":"Row7", "MinerID":1030, "cards":9,"IPAddress":"10.0.1.88", "maxhash":279.7470, "hash":274.290,"Min30":0,"Hr2":0,"Hr6":0,"D1":1,"D2":1, "gpus":[{"hash":30.262, "temp":"67", "fan":83},{"hash":30.296, "temp":"62", "fan":83},{"hash":31.081, "temp":"50", "fan":83},{"hash":30.844, "temp":"52", "fan":83},{"hash":30.324, "temp":"69", "fan":83},{"hash":30.327, "temp":"65", "fan":83},{"hash":30.326, "temp":"65", "fan":83},{"hash":30.312, "temp":"63", "fan":83},{"hash":30.515, "temp":"51", "fan":83}]}]}