{"MaxTotalHashRate":1983.9180,"CurrentTotalHashRate":1943.257,"LastUpdateDate":"Feb 23 2018  8:14AM","RIGs":9,"GPUs":65,"Miners":[{ "miner":"Miner1", "MinerID":1012, "cards":7,"IPAddress":"10.0.1.61", "maxhash":210.9380, "hash":203.714,"Min30":0,"Hr2":0,"Hr6":0,"D1":0,"D2":2, "gpus":[{"hash":28.759, "temp":"58", "fan":83},{"hash":28.788, "temp":"56", "fan":83},{"hash":28.765, "temp":"58", "fan":83},{"hash":29.077, "temp":"59", "fan":83},{"hash":29.407, "temp":"48", "fan":83},{"hash":30.153, "temp":"43", "fan":83},{"hash":28.763, "temp":"54", "fan":83}]},{ "miner":"Miner11", "MinerID":1020, "cards":7,"IPAddress":"10.0.1.37", "maxhash":209.6360, "hash":197.351,"Min30":0,"Hr2":0,"Hr6":0,"D1":0,"D2":0, "gpus":[{"hash":29.381, "temp":"57", "fan":83},{"hash":29.375, "temp":"51", "fan":83},{"hash":29.985, "temp":"50", "fan":83},{"hash":19.984, "temp":"52", "fan":83},{"hash":29.949, "temp":"50", "fan":83},{"hash":29.981, "temp":"71", "fan":83},{"hash":28.693, "temp":"52", "fan":83}]},{ "miner":"Miner12", "MinerID":1016, "cards":8,"IPAddress":"10.0.1.63", "maxhash":242.2880, "hash":240.587,"Min30":0,"Hr2":0,"Hr6":0,"D1":0,"D2":1, "gpus":[{"hash":30.005, "temp":"60", "fan":83},{"hash":30.003, "temp":"67", "fan":83},{"hash":30.002, "temp":"58", "fan":83},{"hash":29.997, "temp":"52", "fan":83},{"hash":30.293, "temp":"54", "fan":83},{"hash":30.006, "temp":"58", "fan":83},{"hash":30.003, "temp":"57", "fan":83},{"hash":30.273, "temp":"62", "fan":83}]},{ "miner":"Miner13", "MinerID":1021, "cards":8,"IPAddress":"10.0.1.5", "maxhash":242.5680, "hash":240.557,"Min30":0,"Hr2":0,"Hr6":0,"D1":0,"D2":0, "gpus":[{"hash":30.000, "temp":"61", "fan":83},{"hash":30.056, "temp":"59", "fan":83},{"hash":30.048, "temp":"59", "fan":83},{"hash":30.319, "temp":"56", "fan":83},{"hash":30.049, "temp":"55", "fan":83},{"hash":29.998, "temp":"58", "fan":83},{"hash":30.062, "temp":"55", "fan":83},{"hash":30.022, "temp":"60", "fan":83}]},{ "miner":"Miner14", "MinerID":1014, "cards":7,"IPAddress":"10.0.1.88", "maxhash":219.2400, "hash":210.527,"Min30":0,"Hr2":0,"Hr6":0,"D1":0,"D2":0, "gpus":[{"hash":31.303, "temp":"47", "fan":83},{"hash":28.980, "temp":"44", "fan":83},{"hash":29.978, "temp":"58", "fan":83},{"hash":29.982, "temp":"58", "fan":83},{"hash":28.989, "temp":"60", "fan":83},{"hash":31.306, "temp":"47", "fan":83},{"hash":29.986, "temp":"68", "fan":83}]},{ "miner":"Miner21", "MinerID":1017, "cards":8,"IPAddress":"10.0.1.50", "maxhash":239.7280, "hash":238.841,"Min30":0,"Hr2":0,"Hr6":0,"D1":0,"D2":0, "gpus":[{"hash":29.972, "temp":"67", "fan":83},{"hash":29.379, "temp":"59", "fan":83},{"hash":29.994, "temp":"53", "fan":83},{"hash":29.932, "temp":"59", "fan":83},{"hash":29.954, "temp":"65", "fan":83},{"hash":29.963, "temp":"71", "fan":83},{"hash":29.678, "temp":"71", "fan":83},{"hash":29.966, "temp":"65", "fan":83}]},{ "miner":"Miner22", "MinerID":1018, "cards":8,"IPAddress":"10.0.1.65", "maxhash":249.3360, "hash":248.396,"Min30":0,"Hr2":0,"Hr6":0,"D1":0,"D2":1, "gpus":[{"hash":31.134, "temp":"52", "fan":80},{"hash":30.914, "temp":"50", "fan":80},{"hash":31.125, "temp":"53", "fan":80},{"hash":30.914, "temp":"43", "fan":80},{"hash":31.134, "temp":"51", "fan":80},{"hash":31.140, "temp":"56", "fan":80},{"hash":31.126, "temp":"52", "fan":80},{"hash":30.907, "temp":"48", "fan":80}]},{ "miner":"Miner23", "MinerID":1022, "cards":8,"IPAddress":"10.0.1.113", "maxhash":250.2800, "hash":247.971,"Min30":0,"Hr2":0,"Hr6":0,"D1":0,"D2":0, "gpus":[{"hash":31.275, "temp":"50", "fan":80},{"hash":29.034, "temp":"64", "fan":80},{"hash":31.277, "temp":"51", "fan":80},{"hash":31.304, "temp":"53", "fan":80},{"hash":31.244, "temp":"55", "fan":80},{"hash":31.327, "temp":"54", "fan":80},{"hash":31.236, "temp":"52", "fan":80},{"hash":31.270, "temp":"54", "fan":80}]},{ "miner":"Miner24", "MinerID":1023, "cards":4,"IPAddress":"10.0.1.70", "maxhash":119.9040, "hash":115.313,"Min30":0,"Hr2":0,"Hr6":0,"D1":0,"D2":0, "gpus":[{"hash":28.597, "temp":"43", "fan":83},{"hash":28.972, "temp":"48", "fan":83},{"hash":29.943, "temp":"44", "fan":83},{"hash":27.799, "temp":"50", "fan":83}]}]}